[{
  "additional_details": {},
  "availability_domain": null,
  "compartment_id": "ocid1.compartment.oc1..aaaaaaaa2ak2x2y5tgpzm3iq3u7wtstrijneiuit525ctyjltj6vvupnzbla",
  "defined_tags": {
    "osc": {
      "automatic_shutdown": "17:00_UTC",
      "automatic_startup": "07:00_UTC",
      "created-by": "oscemea001/jackie.boyle@oracle.com\t",
      "date": "2020-08-05T15:49:30.108Z",
      "type": "user"
    }
  },
  "display_name": "ecce-cl1",
  "freeform_tags": {},
  "identifier": "ocid1.compartment.oc1..aaaaaaaassbyagwbymjd3oe6juk55hkfgzq5v2xkqlums5gxszxodtqvox2a",
  "identity_context": {},
  "lifecycle_state": "ACTIVE",
  "resource_type": "Compartment",
  "search_context": null,
  "system_tags": {},
  "time_created": "2020-08-05T15:49:30.169000+00:00"
}, {
  "additional_details": {},
  "availability_domain": null,
  "compartment_id": "ocid1.compartment.oc1..aaaaaaaa2ak2x2y5tgpzm3iq3u7wtstrijneiuit525ctyjltj6vvupnzbla",
  "defined_tags": {
    "Oracle-Tags": {
      "CreatedBy": "oscemea001/jackie.boyle@oracle.com",
      "CreatedOn": "2023-01-12T16:52:18.902Z"
    },
    "osc": {
      "automatic_shutdown": "17:00_UTC",
      "automatic_startup": "07:00_UTC",
      "type": "user"
    },
    "osc_exacc": {
      "DB-Comments": "Used for: xxxx. Sys password: xxxxx",
      "scale_down_ocpus": "16",
      "scale_down_time": "no_autoscale",
      "scale_up_ocpus": "16",
      "scale_up_time": "no_autoscale"
    }
  },
  "display_name": "ecce-cl2",
  "freeform_tags": {},
  "identifier": "ocid1.compartment.oc1..aaaaaaaajo5ccsj4jxibx7rrpjvqqorbxtznniu3ycgkzztcl2yipu5wyqhq",
  "identity_context": {},
  "lifecycle_state": "ACTIVE",
  "resource_type": "Compartment",
  "search_context": null,
  "system_tags": {},
  "time_created": "2023-01-12T16:52:18.960000+00:00"
}, {
  "additional_details": {},
  "availability_domain": null,
  "compartment_id": "ocid1.compartment.oc1..aaaaaaaa2ak2x2y5tgpzm3iq3u7wtstrijneiuit525ctyjltj6vvupnzbla",
  "defined_tags": {
    "Oracle-Tags": {
      "CreatedBy": "oscemea001/jackie.boyle@oracle.com",
      "CreatedOn": "2023-01-12T19:52:34.839Z"
    },
    "osc": {
      "automatic_shutdown": "17:00_UTC",
      "automatic_startup": "07:00_UTC",
      "type": "user"
    },
    "osc_exacc": {
      "DB-Comments": "Used for: xxxx. Sys password: xxxxx",
      "scale_down_ocpus": "16",
      "scale_down_time": "no_autoscale",
      "scale_up_ocpus": "16",
      "scale_up_time": "no_autoscale"
    }
  },
  "display_name": "ecce-cl3",
  "freeform_tags": {},
  "identifier": "ocid1.compartment.oc1..aaaaaaaaoh7d6tqowvci2d66de45jnponj3sogek3rycjfuugigs2nuzm6la",
  "identity_context": {},
  "lifecycle_state": "ACTIVE",
  "resource_type": "Compartment",
  "search_context": null,
  "system_tags": {},
  "time_created": "2023-01-12T19:52:34.912000+00:00"
}, {
  "additional_details": {},
  "availability_domain": null,
  "compartment_id": "ocid1.compartment.oc1..aaaaaaaa2ak2x2y5tgpzm3iq3u7wtstrijneiuit525ctyjltj6vvupnzbla",
  "defined_tags": {
    "osc": {
      "automatic_shutdown": "17:00_UTC",
      "automatic_startup": "07:00_UTC",
      "created-by": "oscemea001/jackie.boyle@oracle.com\t",
      "date": "2020-08-05T15:49:30.108Z",
      "type": "user"
    }
  },
  "display_name": "ecce-cl1",
  "freeform_tags": {},
  "identifier": "ocid1.compartment.oc1..aaaaaaaassbyagwbymjd3oe6juk55hkfgzq5v2xkqlums5gxszxodtqvox2a",
  "identity_context": {},
  "lifecycle_state": "ACTIVE",
  "resource_type": "Compartment",
  "search_context": null,
  "system_tags": {},
  "time_created": "2020-08-05T15:49:30.169000+00:00"
}, {
  "additional_details": {},
  "availability_domain": null,
  "compartment_id": "ocid1.compartment.oc1..aaaaaaaa2ak2x2y5tgpzm3iq3u7wtstrijneiuit525ctyjltj6vvupnzbla",
  "defined_tags": {
    "Oracle-Tags": {
      "CreatedBy": "oscemea001/jackie.boyle@oracle.com",
      "CreatedOn": "2023-01-12T16:52:18.902Z"
    },
    "osc": {
      "automatic_shutdown": "17:00_UTC",
      "automatic_startup": "07:00_UTC",
      "type": "user"
    },
    "osc_exacc": {
      "DB-Comments": "Used for: xxxx. Sys password: xxxxx",
      "scale_down_ocpus": "16",
      "scale_down_time": "no_autoscale",
      "scale_up_ocpus": "16",
      "scale_up_time": "no_autoscale"
    }
  },
  "display_name": "ecce-cl2",
  "freeform_tags": {},
  "identifier": "ocid1.compartment.oc1..aaaaaaaajo5ccsj4jxibx7rrpjvqqorbxtznniu3ycgkzztcl2yipu5wyqhq",
  "identity_context": {},
  "lifecycle_state": "ACTIVE",
  "resource_type": "Compartment",
  "search_context": null,
  "system_tags": {},
  "time_created": "2023-01-12T16:52:18.960000+00:00"
}, {
  "additional_details": {},
  "availability_domain": null,
  "compartment_id": "ocid1.compartment.oc1..aaaaaaaa2ak2x2y5tgpzm3iq3u7wtstrijneiuit525ctyjltj6vvupnzbla",
  "defined_tags": {
    "Oracle-Tags": {
      "CreatedBy": "oscemea001/jackie.boyle@oracle.com",
      "CreatedOn": "2023-01-12T19:52:34.839Z"
    },
    "osc": {
      "automatic_shutdown": "17:00_UTC",
      "automatic_startup": "07:00_UTC",
      "type": "user"
    },
    "osc_exacc": {
      "DB-Comments": "Used for: xxxx. Sys password: xxxxx",
      "scale_down_ocpus": "16",
      "scale_down_time": "no_autoscale",
      "scale_up_ocpus": "16",
      "scale_up_time": "no_autoscale"
    }
  },
  "display_name": "ecce-cl3",
  "freeform_tags": {},
  "identifier": "ocid1.compartment.oc1..aaaaaaaaoh7d6tqowvci2d66de45jnponj3sogek3rycjfuugigs2nuzm6la",
  "identity_context": {},
  "lifecycle_state": "ACTIVE",
  "resource_type": "Compartment",
  "search_context": null,
  "system_tags": {},
  "time_created": "2023-01-12T19:52:34.912000+00:00"
}, {
  "additional_details": {},
  "availability_domain": null,
  "compartment_id": "ocid1.compartment.oc1..aaaaaaaa2ak2x2y5tgpzm3iq3u7wtstrijneiuit525ctyjltj6vvupnzbla",
  "defined_tags": {
    "osc": {
      "automatic_shutdown": "17:00_UTC",
      "automatic_startup": "07:00_UTC",
      "created-by": "oscemea001/jackie.boyle@oracle.com\t",
      "date": "2020-08-05T15:49:30.108Z",
      "type": "user"
    }
  },
  "display_name": "ecce-cl1",
  "freeform_tags": {},
  "identifier": "ocid1.compartment.oc1..aaaaaaaassbyagwbymjd3oe6juk55hkfgzq5v2xkqlums5gxszxodtqvox2a",
  "identity_context": {},
  "lifecycle_state": "ACTIVE",
  "resource_type": "Compartment",
  "search_context": null,
  "system_tags": {},
  "time_created": "2020-08-05T15:49:30.169000+00:00"
}, {
  "additional_details": {},
  "availability_domain": null,
  "compartment_id": "ocid1.compartment.oc1..aaaaaaaa2ak2x2y5tgpzm3iq3u7wtstrijneiuit525ctyjltj6vvupnzbla",
  "defined_tags": {
    "Oracle-Tags": {
      "CreatedBy": "oscemea001/jackie.boyle@oracle.com",
      "CreatedOn": "2023-01-12T16:52:18.902Z"
    },
    "osc": {
      "automatic_shutdown": "17:00_UTC",
      "automatic_startup": "07:00_UTC",
      "type": "user"
    },
    "osc_exacc": {
      "DB-Comments": "Used for: xxxx. Sys password: xxxxx",
      "scale_down_ocpus": "16",
      "scale_down_time": "no_autoscale",
      "scale_up_ocpus": "16",
      "scale_up_time": "no_autoscale"
    }
  },
  "display_name": "ecce-cl2",
  "freeform_tags": {},
  "identifier": "ocid1.compartment.oc1..aaaaaaaajo5ccsj4jxibx7rrpjvqqorbxtznniu3ycgkzztcl2yipu5wyqhq",
  "identity_context": {},
  "lifecycle_state": "ACTIVE",
  "resource_type": "Compartment",
  "search_context": null,
  "system_tags": {},
  "time_created": "2023-01-12T16:52:18.960000+00:00"
}, {
  "additional_details": {},
  "availability_domain": null,
  "compartment_id": "ocid1.compartment.oc1..aaaaaaaa2ak2x2y5tgpzm3iq3u7wtstrijneiuit525ctyjltj6vvupnzbla",
  "defined_tags": {
    "Oracle-Tags": {
      "CreatedBy": "oscemea001/jackie.boyle@oracle.com",
      "CreatedOn": "2023-01-12T19:52:34.839Z"
    },
    "osc": {
      "automatic_shutdown": "17:00_UTC",
      "automatic_startup": "07:00_UTC",
      "type": "user"
    },
    "osc_exacc": {
      "DB-Comments": "Used for: xxxx. Sys password: xxxxx",
      "scale_down_ocpus": "16",
      "scale_down_time": "no_autoscale",
      "scale_up_ocpus": "16",
      "scale_up_time": "no_autoscale"
    }
  },
  "display_name": "ecce-cl3",
  "freeform_tags": {},
  "identifier": "ocid1.compartment.oc1..aaaaaaaaoh7d6tqowvci2d66de45jnponj3sogek3rycjfuugigs2nuzm6la",
  "identity_context": {},
  "lifecycle_state": "ACTIVE",
  "resource_type": "Compartment",
  "search_context": null,
  "system_tags": {},
  "time_created": "2023-01-12T19:52:34.912000+00:00"
}, {
  "additional_details": {},
  "availability_domain": null,
  "compartment_id": "ocid1.compartment.oc1..aaaaaaaa2ak2x2y5tgpzm3iq3u7wtstrijneiuit525ctyjltj6vvupnzbla",
  "defined_tags": {
    "osc": {
      "automatic_shutdown": "17:00_UTC",
      "automatic_startup": "07:00_UTC",
      "created-by": "oscemea001/jackie.boyle@oracle.com\t",
      "date": "2020-08-05T15:49:30.108Z",
      "type": "user"
    }
  },
  "display_name": "ecce-cl1",
  "freeform_tags": {},
  "identifier": "ocid1.compartment.oc1..aaaaaaaassbyagwbymjd3oe6juk55hkfgzq5v2xkqlums5gxszxodtqvox2a",
  "identity_context": {},
  "lifecycle_state": "ACTIVE",
  "resource_type": "Compartment",
  "search_context": null,
  "system_tags": {},
  "time_created": "2020-08-05T15:49:30.169000+00:00"
}, {
  "additional_details": {},
  "availability_domain": null,
  "compartment_id": "ocid1.compartment.oc1..aaaaaaaa2ak2x2y5tgpzm3iq3u7wtstrijneiuit525ctyjltj6vvupnzbla",
  "defined_tags": {
    "Oracle-Tags": {
      "CreatedBy": "oscemea001/jackie.boyle@oracle.com",
      "CreatedOn": "2023-01-12T16:52:18.902Z"
    },
    "osc": {
      "automatic_shutdown": "17:00_UTC",
      "automatic_startup": "07:00_UTC",
      "type": "user"
    },
    "osc_exacc": {
      "DB-Comments": "Used for: xxxx. Sys password: xxxxx",
      "scale_down_ocpus": "16",
      "scale_down_time": "no_autoscale",
      "scale_up_ocpus": "16",
      "scale_up_time": "no_autoscale"
    }
  },
  "display_name": "ecce-cl2",
  "freeform_tags": {},
  "identifier": "ocid1.compartment.oc1..aaaaaaaajo5ccsj4jxibx7rrpjvqqorbxtznniu3ycgkzztcl2yipu5wyqhq",
  "identity_context": {},
  "lifecycle_state": "ACTIVE",
  "resource_type": "Compartment",
  "search_context": null,
  "system_tags": {},
  "time_created": "2023-01-12T16:52:18.960000+00:00"
}, {
  "additional_details": {},
  "availability_domain": null,
  "compartment_id": "ocid1.compartment.oc1..aaaaaaaa2ak2x2y5tgpzm3iq3u7wtstrijneiuit525ctyjltj6vvupnzbla",
  "defined_tags": {
    "Oracle-Tags": {
      "CreatedBy": "oscemea001/jackie.boyle@oracle.com",
      "CreatedOn": "2023-01-12T19:52:34.839Z"
    },
    "osc": {
      "automatic_shutdown": "17:00_UTC",
      "automatic_startup": "07:00_UTC",
      "type": "user"
    },
    "osc_exacc": {
      "DB-Comments": "Used for: xxxx. Sys password: xxxxx",
      "scale_down_ocpus": "16",
      "scale_down_time": "no_autoscale",
      "scale_up_ocpus": "16",
      "scale_up_time": "no_autoscale"
    }
  },
  "display_name": "ecce-cl3",
  "freeform_tags": {},
  "identifier": "ocid1.compartment.oc1..aaaaaaaaoh7d6tqowvci2d66de45jnponj3sogek3rycjfuugigs2nuzm6la",
  "identity_context": {},
  "lifecycle_state": "ACTIVE",
  "resource_type": "Compartment",
  "search_context": null,
  "system_tags": {},
  "time_created": "2023-01-12T19:52:34.912000+00:00"
}, {
  "additional_details": {},
  "availability_domain": null,
  "compartment_id": "ocid1.compartment.oc1..aaaaaaaa2ak2x2y5tgpzm3iq3u7wtstrijneiuit525ctyjltj6vvupnzbla",
  "defined_tags": {
    "osc": {
      "automatic_shutdown": "17:00_UTC",
      "automatic_startup": "07:00_UTC",
      "created-by": "oscemea001/jackie.boyle@oracle.com\t",
      "date": "2020-08-05T15:49:30.108Z",
      "type": "user"
    }
  },
  "display_name": "ecce-cl1",
  "freeform_tags": {},
  "identifier": "ocid1.compartment.oc1..aaaaaaaassbyagwbymjd3oe6juk55hkfgzq5v2xkqlums5gxszxodtqvox2a",
  "identity_context": {},
  "lifecycle_state": "ACTIVE",
  "resource_type": "Compartment",
  "search_context": null,
  "system_tags": {},
  "time_created": "2020-08-05T15:49:30.169000+00:00"
}, {
  "additional_details": {},
  "availability_domain": null,
  "compartment_id": "ocid1.compartment.oc1..aaaaaaaa2ak2x2y5tgpzm3iq3u7wtstrijneiuit525ctyjltj6vvupnzbla",
  "defined_tags": {
    "Oracle-Tags": {
      "CreatedBy": "oscemea001/jackie.boyle@oracle.com",
      "CreatedOn": "2023-01-12T16:52:18.902Z"
    },
    "osc": {
      "automatic_shutdown": "17:00_UTC",
      "automatic_startup": "07:00_UTC",
      "type": "user"
    },
    "osc_exacc": {
      "DB-Comments": "Used for: xxxx. Sys password: xxxxx",
      "scale_down_ocpus": "16",
      "scale_down_time": "no_autoscale",
      "scale_up_ocpus": "16",
      "scale_up_time": "no_autoscale"
    }
  },
  "display_name": "ecce-cl2",
  "freeform_tags": {},
  "identifier": "ocid1.compartment.oc1..aaaaaaaajo5ccsj4jxibx7rrpjvqqorbxtznniu3ycgkzztcl2yipu5wyqhq",
  "identity_context": {},
  "lifecycle_state": "ACTIVE",
  "resource_type": "Compartment",
  "search_context": null,
  "system_tags": {},
  "time_created": "2023-01-12T16:52:18.960000+00:00"
}, {
  "additional_details": {},
  "availability_domain": null,
  "compartment_id": "ocid1.compartment.oc1..aaaaaaaa2ak2x2y5tgpzm3iq3u7wtstrijneiuit525ctyjltj6vvupnzbla",
  "defined_tags": {
    "Oracle-Tags": {
      "CreatedBy": "oscemea001/jackie.boyle@oracle.com",
      "CreatedOn": "2023-01-12T19:52:34.839Z"
    },
    "osc": {
      "automatic_shutdown": "17:00_UTC",
      "automatic_startup": "07:00_UTC",
      "type": "user"
    },
    "osc_exacc": {
      "DB-Comments": "Used for: xxxx. Sys password: xxxxx",
      "scale_down_ocpus": "16",
      "scale_down_time": "no_autoscale",
      "scale_up_ocpus": "16",
      "scale_up_time": "no_autoscale"
    }
  },
  "display_name": "ecce-cl3",
  "freeform_tags": {},
  "identifier": "ocid1.compartment.oc1..aaaaaaaaoh7d6tqowvci2d66de45jnponj3sogek3rycjfuugigs2nuzm6la",
  "identity_context": {},
  "lifecycle_state": "ACTIVE",
  "resource_type": "Compartment",
  "search_context": null,
  "system_tags": {},
  "time_created": "2023-01-12T19:52:34.912000+00:00"
}, {
  "additional_details": {},
  "availability_domain": null,
  "compartment_id": "ocid1.compartment.oc1..aaaaaaaa2ak2x2y5tgpzm3iq3u7wtstrijneiuit525ctyjltj6vvupnzbla",
  "defined_tags": {
    "osc": {
      "automatic_shutdown": "17:00_UTC",
      "automatic_startup": "07:00_UTC",
      "created-by": "oscemea001/jackie.boyle@oracle.com\t",
      "date": "2020-08-05T15:49:30.108Z",
      "type": "user"
    }
  },
  "display_name": "ecce-cl1",
  "freeform_tags": {},
  "identifier": "ocid1.compartment.oc1..aaaaaaaassbyagwbymjd3oe6juk55hkfgzq5v2xkqlums5gxszxodtqvox2a",
  "identity_context": {},
  "lifecycle_state": "ACTIVE",
  "resource_type": "Compartment",
  "search_context": null,
  "system_tags": {},
  "time_created": "2020-08-05T15:49:30.169000+00:00"
}, {
  "additional_details": {},
  "availability_domain": null,
  "compartment_id": "ocid1.compartment.oc1..aaaaaaaa2ak2x2y5tgpzm3iq3u7wtstrijneiuit525ctyjltj6vvupnzbla",
  "defined_tags": {
    "Oracle-Tags": {
      "CreatedBy": "oscemea001/jackie.boyle@oracle.com",
      "CreatedOn": "2023-01-12T16:52:18.902Z"
    },
    "osc": {
      "automatic_shutdown": "17:00_UTC",
      "automatic_startup": "07:00_UTC",
      "type": "user"
    },
    "osc_exacc": {
      "DB-Comments": "Used for: xxxx. Sys password: xxxxx",
      "scale_down_ocpus": "16",
      "scale_down_time": "no_autoscale",
      "scale_up_ocpus": "16",
      "scale_up_time": "no_autoscale"
    }
  },
  "display_name": "ecce-cl2",
  "freeform_tags": {},
  "identifier": "ocid1.compartment.oc1..aaaaaaaajo5ccsj4jxibx7rrpjvqqorbxtznniu3ycgkzztcl2yipu5wyqhq",
  "identity_context": {},
  "lifecycle_state": "ACTIVE",
  "resource_type": "Compartment",
  "search_context": null,
  "system_tags": {},
  "time_created": "2023-01-12T16:52:18.960000+00:00"
}, {
  "additional_details": {},
  "availability_domain": null,
  "compartment_id": "ocid1.compartment.oc1..aaaaaaaa2ak2x2y5tgpzm3iq3u7wtstrijneiuit525ctyjltj6vvupnzbla",
  "defined_tags": {
    "Oracle-Tags": {
      "CreatedBy": "oscemea001/jackie.boyle@oracle.com",
      "CreatedOn": "2023-01-12T19:52:34.839Z"
    },
    "osc": {
      "automatic_shutdown": "17:00_UTC",
      "automatic_startup": "07:00_UTC",
      "type": "user"
    },
    "osc_exacc": {
      "DB-Comments": "Used for: xxxx. Sys password: xxxxx",
      "scale_down_ocpus": "16",
      "scale_down_time": "no_autoscale",
      "scale_up_ocpus": "16",
      "scale_up_time": "no_autoscale"
    }
  },
  "display_name": "ecce-cl3",
  "freeform_tags": {},
  "identifier": "ocid1.compartment.oc1..aaaaaaaaoh7d6tqowvci2d66de45jnponj3sogek3rycjfuugigs2nuzm6la",
  "identity_context": {},
  "lifecycle_state": "ACTIVE",
  "resource_type": "Compartment",
  "search_context": null,
  "system_tags": {},
  "time_created": "2023-01-12T19:52:34.912000+00:00"
}, {
  "additional_details": {},
  "availability_domain": null,
  "compartment_id": "ocid1.compartment.oc1..aaaaaaaa2ak2x2y5tgpzm3iq3u7wtstrijneiuit525ctyjltj6vvupnzbla",
  "defined_tags": {},
  "display_name": "SA_1654855070324",
  "freeform_tags": {},
  "identifier": "ocid1.datasafesecurityassessment.oc1.eu-frankfurt-1.abtheljrqfmksfxvlnvpb4lh2cd33vksns2d2acvutljdicbfabn7zc3izyq",
  "identity_context": {},
  "lifecycle_state": "SUCCEEDED",
  "resource_type": "DataSafeSecurityAssessment",
  "search_context": null,
  "system_tags": {},
  "time_created": "2022-06-10T09:57:50.328000+00:00"
}, {
  "additional_details": {},
  "availability_domain": null,
  "compartment_id": "ocid1.compartment.oc1..aaaaaaaa2ak2x2y5tgpzm3iq3u7wtstrijneiuit525ctyjltj6vvupnzbla",
  "defined_tags": {},
  "display_name": "UA_1654856382603",
  "freeform_tags": {},
  "identifier": "ocid1.datasafeuserassessment.oc1.eu-frankfurt-1.abtheljrjsarwb7rnc2yhiw7k6ivz4ay7pzaao2rpg7ee44lk2tfb2re544q",
  "identity_context": {},
  "lifecycle_state": "SUCCEEDED",
  "resource_type": "DataSafeUserAssessment",
  "search_context": null,
  "system_tags": {},
  "time_created": "2022-06-10T10:19:42.607000+00:00"
}, {
  "additional_details": {},
  "availability_domain": null,
  "compartment_id": "ocid1.compartment.oc1..aaaaaaaa2ak2x2y5tgpzm3iq3u7wtstrijneiuit525ctyjltj6vvupnzbla",
  "defined_tags": {
    "osc": {
      "automatic_shutdown": "17:00_UTC",
      "automatic_startup": "07:00_UTC",
      "created-by": "oscemea001/jackie.boyle@oracle.com\t",
      "date": "2020-08-05T15:49:30.108Z",
      "type": "user"
    }
  },
  "display_name": "ecce-cl1",
  "freeform_tags": {},
  "identifier": "ocid1.compartment.oc1..aaaaaaaassbyagwbymjd3oe6juk55hkfgzq5v2xkqlums5gxszxodtqvox2a",
  "identity_context": {},
  "lifecycle_state": "ACTIVE",
  "resource_type": "Compartment",
  "search_context": null,
  "system_tags": {},
  "time_created": "2020-08-05T15:49:30.169000+00:00"
}, {
  "additional_details": {},
  "availability_domain": null,
  "compartment_id": "ocid1.compartment.oc1..aaaaaaaa2ak2x2y5tgpzm3iq3u7wtstrijneiuit525ctyjltj6vvupnzbla",
  "defined_tags": {
    "Oracle-Tags": {
      "CreatedBy": "oscemea001/jackie.boyle@oracle.com",
      "CreatedOn": "2023-01-12T16:52:18.902Z"
    },
    "osc": {
      "automatic_shutdown": "17:00_UTC",
      "automatic_startup": "07:00_UTC",
      "type": "user"
    },
    "osc_exacc": {
      "DB-Comments": "Used for: xxxx. Sys password: xxxxx",
      "scale_down_ocpus": "16",
      "scale_down_time": "no_autoscale",
      "scale_up_ocpus": "16",
      "scale_up_time": "no_autoscale"
    }
  },
  "display_name": "ecce-cl2",
  "freeform_tags": {},
  "identifier": "ocid1.compartment.oc1..aaaaaaaajo5ccsj4jxibx7rrpjvqqorbxtznniu3ycgkzztcl2yipu5wyqhq",
  "identity_context": {},
  "lifecycle_state": "ACTIVE",
  "resource_type": "Compartment",
  "search_context": null,
  "system_tags": {},
  "time_created": "2023-01-12T16:52:18.960000+00:00"
}, {
  "additional_details": {},
  "availability_domain": null,
  "compartment_id": "ocid1.compartment.oc1..aaaaaaaa2ak2x2y5tgpzm3iq3u7wtstrijneiuit525ctyjltj6vvupnzbla",
  "defined_tags": {
    "Oracle-Tags": {
      "CreatedBy": "oscemea001/jackie.boyle@oracle.com",
      "CreatedOn": "2023-01-12T19:52:34.839Z"
    },
    "osc": {
      "automatic_shutdown": "17:00_UTC",
      "automatic_startup": "07:00_UTC",
      "type": "user"
    },
    "osc_exacc": {
      "DB-Comments": "Used for: xxxx. Sys password: xxxxx",
      "scale_down_ocpus": "16",
      "scale_down_time": "no_autoscale",
      "scale_up_ocpus": "16",
      "scale_up_time": "no_autoscale"
    }
  },
  "display_name": "ecce-cl3",
  "freeform_tags": {},
  "identifier": "ocid1.compartment.oc1..aaaaaaaaoh7d6tqowvci2d66de45jnponj3sogek3rycjfuugigs2nuzm6la",
  "identity_context": {},
  "lifecycle_state": "ACTIVE",
  "resource_type": "Compartment",
  "search_context": null,
  "system_tags": {},
  "time_created": "2023-01-12T19:52:34.912000+00:00"
}, {
  "additional_details": {},
  "availability_domain": null,
  "compartment_id": "ocid1.compartment.oc1..aaaaaaaa2ak2x2y5tgpzm3iq3u7wtstrijneiuit525ctyjltj6vvupnzbla",
  "defined_tags": {
    "osc": {
      "automatic_shutdown": "17:00_UTC",
      "automatic_startup": "07:00_UTC",
      "created-by": "oscemea001/jackie.boyle@oracle.com\t",
      "date": "2020-08-05T15:49:30.108Z",
      "type": "user"
    }
  },
  "display_name": "ecce-cl1",
  "freeform_tags": {},
  "identifier": "ocid1.compartment.oc1..aaaaaaaassbyagwbymjd3oe6juk55hkfgzq5v2xkqlums5gxszxodtqvox2a",
  "identity_context": {},
  "lifecycle_state": "ACTIVE",
  "resource_type": "Compartment",
  "search_context": null,
  "system_tags": {},
  "time_created": "2020-08-05T15:49:30.169000+00:00"
}, {
  "additional_details": {},
  "availability_domain": null,
  "compartment_id": "ocid1.compartment.oc1..aaaaaaaa2ak2x2y5tgpzm3iq3u7wtstrijneiuit525ctyjltj6vvupnzbla",
  "defined_tags": {
    "Oracle-Tags": {
      "CreatedBy": "oscemea001/jackie.boyle@oracle.com",
      "CreatedOn": "2023-01-12T16:52:18.902Z"
    },
    "osc": {
      "automatic_shutdown": "17:00_UTC",
      "automatic_startup": "07:00_UTC",
      "type": "user"
    },
    "osc_exacc": {
      "DB-Comments": "Used for: xxxx. Sys password: xxxxx",
      "scale_down_ocpus": "16",
      "scale_down_time": "no_autoscale",
      "scale_up_ocpus": "16",
      "scale_up_time": "no_autoscale"
    }
  },
  "display_name": "ecce-cl2",
  "freeform_tags": {},
  "identifier": "ocid1.compartment.oc1..aaaaaaaajo5ccsj4jxibx7rrpjvqqorbxtznniu3ycgkzztcl2yipu5wyqhq",
  "identity_context": {},
  "lifecycle_state": "ACTIVE",
  "resource_type": "Compartment",
  "search_context": null,
  "system_tags": {},
  "time_created": "2023-01-12T16:52:18.960000+00:00"
}, {
  "additional_details": {},
  "availability_domain": null,
  "compartment_id": "ocid1.compartment.oc1..aaaaaaaa2ak2x2y5tgpzm3iq3u7wtstrijneiuit525ctyjltj6vvupnzbla",
  "defined_tags": {
    "Oracle-Tags": {
      "CreatedBy": "oscemea001/jackie.boyle@oracle.com",
      "CreatedOn": "2023-01-12T19:52:34.839Z"
    },
    "osc": {
      "automatic_shutdown": "17:00_UTC",
      "automatic_startup": "07:00_UTC",
      "type": "user"
    },
    "osc_exacc": {
      "DB-Comments": "Used for: xxxx. Sys password: xxxxx",
      "scale_down_ocpus": "16",
      "scale_down_time": "no_autoscale",
      "scale_up_ocpus": "16",
      "scale_up_time": "no_autoscale"
    }
  },
  "display_name": "ecce-cl3",
  "freeform_tags": {},
  "identifier": "ocid1.compartment.oc1..aaaaaaaaoh7d6tqowvci2d66de45jnponj3sogek3rycjfuugigs2nuzm6la",
  "identity_context": {},
  "lifecycle_state": "ACTIVE",
  "resource_type": "Compartment",
  "search_context": null,
  "system_tags": {},
  "time_created": "2023-01-12T19:52:34.912000+00:00"
}, {
  "additional_details": {},
  "availability_domain": null,
  "compartment_id": "ocid1.compartment.oc1..aaaaaaaa2ak2x2y5tgpzm3iq3u7wtstrijneiuit525ctyjltj6vvupnzbla",
  "defined_tags": {
    "osc": {
      "automatic_shutdown": "17:00_UTC",
      "automatic_startup": "07:00_UTC",
      "created-by": "oscemea001/jackie.boyle@oracle.com\t",
      "date": "2020-08-05T15:49:30.108Z",
      "type": "user"
    }
  },
  "display_name": "ecce-cl1",
  "freeform_tags": {},
  "identifier": "ocid1.compartment.oc1..aaaaaaaassbyagwbymjd3oe6juk55hkfgzq5v2xkqlums5gxszxodtqvox2a",
  "identity_context": {},
  "lifecycle_state": "ACTIVE",
  "resource_type": "Compartment",
  "search_context": null,
  "system_tags": {},
  "time_created": "2020-08-05T15:49:30.169000+00:00"
}, {
  "additional_details": {},
  "availability_domain": null,
  "compartment_id": "ocid1.compartment.oc1..aaaaaaaa2ak2x2y5tgpzm3iq3u7wtstrijneiuit525ctyjltj6vvupnzbla",
  "defined_tags": {
    "Oracle-Tags": {
      "CreatedBy": "oscemea001/jackie.boyle@oracle.com",
      "CreatedOn": "2023-01-12T16:52:18.902Z"
    },
    "osc": {
      "automatic_shutdown": "17:00_UTC",
      "automatic_startup": "07:00_UTC",
      "type": "user"
    },
    "osc_exacc": {
      "DB-Comments": "Used for: xxxx. Sys password: xxxxx",
      "scale_down_ocpus": "16",
      "scale_down_time": "no_autoscale",
      "scale_up_ocpus": "16",
      "scale_up_time": "no_autoscale"
    }
  },
  "display_name": "ecce-cl2",
  "freeform_tags": {},
  "identifier": "ocid1.compartment.oc1..aaaaaaaajo5ccsj4jxibx7rrpjvqqorbxtznniu3ycgkzztcl2yipu5wyqhq",
  "identity_context": {},
  "lifecycle_state": "ACTIVE",
  "resource_type": "Compartment",
  "search_context": null,
  "system_tags": {},
  "time_created": "2023-01-12T16:52:18.960000+00:00"
}, {
  "additional_details": {},
  "availability_domain": null,
  "compartment_id": "ocid1.compartment.oc1..aaaaaaaa2ak2x2y5tgpzm3iq3u7wtstrijneiuit525ctyjltj6vvupnzbla",
  "defined_tags": {
    "Oracle-Tags": {
      "CreatedBy": "oscemea001/jackie.boyle@oracle.com",
      "CreatedOn": "2023-01-12T19:52:34.839Z"
    },
    "osc": {
      "automatic_shutdown": "17:00_UTC",
      "automatic_startup": "07:00_UTC",
      "type": "user"
    },
    "osc_exacc": {
      "DB-Comments": "Used for: xxxx. Sys password: xxxxx",
      "scale_down_ocpus": "16",
      "scale_down_time": "no_autoscale",
      "scale_up_ocpus": "16",
      "scale_up_time": "no_autoscale"
    }
  },
  "display_name": "ecce-cl3",
  "freeform_tags": {},
  "identifier": "ocid1.compartment.oc1..aaaaaaaaoh7d6tqowvci2d66de45jnponj3sogek3rycjfuugigs2nuzm6la",
  "identity_context": {},
  "lifecycle_state": "ACTIVE",
  "resource_type": "Compartment",
  "search_context": null,
  "system_tags": {},
  "time_created": "2023-01-12T19:52:34.912000+00:00"
}, {
  "additional_details": {},
  "availability_domain": null,
  "compartment_id": "ocid1.compartment.oc1..aaaaaaaa2ak2x2y5tgpzm3iq3u7wtstrijneiuit525ctyjltj6vvupnzbla",
  "defined_tags": {},
  "display_name": "SA_1654913599100",
  "freeform_tags": {},
  "identifier": "ocid1.datasafesecurityassessment.oc1.iad.abuwcljtrgr76yelygbb54exvt4sa2smohwkenb3yzzstxt55vyhdufxjjda",
  "identity_context": {},
  "lifecycle_state": "SUCCEEDED",
  "resource_type": "DataSafeSecurityAssessment",
  "search_context": null,
  "system_tags": {},
  "time_created": "2022-06-11T02:13:19.111000+00:00"
}, {
  "additional_details": {},
  "availability_domain": null,
  "compartment_id": "ocid1.compartment.oc1..aaaaaaaa2ak2x2y5tgpzm3iq3u7wtstrijneiuit525ctyjltj6vvupnzbla",
  "defined_tags": {},
  "display_name": "UA_1654907644311",
  "freeform_tags": {},
  "identifier": "ocid1.datasafeuserassessment.oc1.iad.abuwcljrwejty4qzcxeu7perkmbngllgz67tquingoodyciuuyamkqt6hrpa",
  "identity_context": {},
  "lifecycle_state": "SUCCEEDED",
  "resource_type": "DataSafeUserAssessment",
  "search_context": null,
  "system_tags": {},
  "time_created": "2022-06-11T00:34:04.336000+00:00"
}, {
  "additional_details": {},
  "availability_domain": null,
  "compartment_id": "ocid1.compartment.oc1..aaaaaaaa2ak2x2y5tgpzm3iq3u7wtstrijneiuit525ctyjltj6vvupnzbla",
  "defined_tags": {
    "osc": {
      "automatic_shutdown": "17:00_UTC",
      "automatic_startup": "07:00_UTC",
      "created-by": "oscemea001/jackie.boyle@oracle.com\t",
      "date": "2020-08-05T15:49:30.108Z",
      "type": "user"
    }
  },
  "display_name": "ecce-cl1",
  "freeform_tags": {},
  "identifier": "ocid1.compartment.oc1..aaaaaaaassbyagwbymjd3oe6juk55hkfgzq5v2xkqlums5gxszxodtqvox2a",
  "identity_context": {},
  "lifecycle_state": "ACTIVE",
  "resource_type": "Compartment",
  "search_context": null,
  "system_tags": {},
  "time_created": "2020-08-05T15:49:30.169000+00:00"
}, {
  "additional_details": {},
  "availability_domain": null,
  "compartment_id": "ocid1.compartment.oc1..aaaaaaaa2ak2x2y5tgpzm3iq3u7wtstrijneiuit525ctyjltj6vvupnzbla",
  "defined_tags": {
    "Oracle-Tags": {
      "CreatedBy": "oscemea001/jackie.boyle@oracle.com",
      "CreatedOn": "2023-01-12T16:52:18.902Z"
    },
    "osc": {
      "automatic_shutdown": "17:00_UTC",
      "automatic_startup": "07:00_UTC",
      "type": "user"
    },
    "osc_exacc": {
      "DB-Comments": "Used for: xxxx. Sys password: xxxxx",
      "scale_down_ocpus": "16",
      "scale_down_time": "no_autoscale",
      "scale_up_ocpus": "16",
      "scale_up_time": "no_autoscale"
    }
  },
  "display_name": "ecce-cl2",
  "freeform_tags": {},
  "identifier": "ocid1.compartment.oc1..aaaaaaaajo5ccsj4jxibx7rrpjvqqorbxtznniu3ycgkzztcl2yipu5wyqhq",
  "identity_context": {},
  "lifecycle_state": "ACTIVE",
  "resource_type": "Compartment",
  "search_context": null,
  "system_tags": {},
  "time_created": "2023-01-12T16:52:18.960000+00:00"
}, {
  "additional_details": {},
  "availability_domain": null,
  "compartment_id": "ocid1.compartment.oc1..aaaaaaaa2ak2x2y5tgpzm3iq3u7wtstrijneiuit525ctyjltj6vvupnzbla",
  "defined_tags": {
    "Oracle-Tags": {
      "CreatedBy": "oscemea001/jackie.boyle@oracle.com",
      "CreatedOn": "2023-01-12T19:52:34.839Z"
    },
    "osc": {
      "automatic_shutdown": "17:00_UTC",
      "automatic_startup": "07:00_UTC",
      "type": "user"
    },
    "osc_exacc": {
      "DB-Comments": "Used for: xxxx. Sys password: xxxxx",
      "scale_down_ocpus": "16",
      "scale_down_time": "no_autoscale",
      "scale_up_ocpus": "16",
      "scale_up_time": "no_autoscale"
    }
  },
  "display_name": "ecce-cl3",
  "freeform_tags": {},
  "identifier": "ocid1.compartment.oc1..aaaaaaaaoh7d6tqowvci2d66de45jnponj3sogek3rycjfuugigs2nuzm6la",
  "identity_context": {},
  "lifecycle_state": "ACTIVE",
  "resource_type": "Compartment",
  "search_context": null,
  "system_tags": {},
  "time_created": "2023-01-12T19:52:34.912000+00:00"
}, {
  "additional_details": {},
  "availability_domain": null,
  "compartment_id": "ocid1.compartment.oc1..aaaaaaaa2ak2x2y5tgpzm3iq3u7wtstrijneiuit525ctyjltj6vvupnzbla",
  "defined_tags": {
    "osc": {
      "automatic_shutdown": "17:00_UTC",
      "automatic_startup": "07:00_UTC",
      "created-by": "oscemea001/jackie.boyle@oracle.com\t",
      "date": "2020-08-05T15:49:30.108Z",
      "type": "user"
    }
  },
  "display_name": "ecce-cl1",
  "freeform_tags": {},
  "identifier": "ocid1.compartment.oc1..aaaaaaaassbyagwbymjd3oe6juk55hkfgzq5v2xkqlums5gxszxodtqvox2a",
  "identity_context": {},
  "lifecycle_state": "ACTIVE",
  "resource_type": "Compartment",
  "search_context": null,
  "system_tags": {},
  "time_created": "2020-08-05T15:49:30.169000+00:00"
}, {
  "additional_details": {},
  "availability_domain": null,
  "compartment_id": "ocid1.compartment.oc1..aaaaaaaa2ak2x2y5tgpzm3iq3u7wtstrijneiuit525ctyjltj6vvupnzbla",
  "defined_tags": {
    "Oracle-Tags": {
      "CreatedBy": "oscemea001/jackie.boyle@oracle.com",
      "CreatedOn": "2023-01-12T16:52:18.902Z"
    },
    "osc": {
      "automatic_shutdown": "17:00_UTC",
      "automatic_startup": "07:00_UTC",
      "type": "user"
    },
    "osc_exacc": {
      "DB-Comments": "Used for: xxxx. Sys password: xxxxx",
      "scale_down_ocpus": "16",
      "scale_down_time": "no_autoscale",
      "scale_up_ocpus": "16",
      "scale_up_time": "no_autoscale"
    }
  },
  "display_name": "ecce-cl2",
  "freeform_tags": {},
  "identifier": "ocid1.compartment.oc1..aaaaaaaajo5ccsj4jxibx7rrpjvqqorbxtznniu3ycgkzztcl2yipu5wyqhq",
  "identity_context": {},
  "lifecycle_state": "ACTIVE",
  "resource_type": "Compartment",
  "search_context": null,
  "system_tags": {},
  "time_created": "2023-01-12T16:52:18.960000+00:00"
}, {
  "additional_details": {},
  "availability_domain": null,
  "compartment_id": "ocid1.compartment.oc1..aaaaaaaa2ak2x2y5tgpzm3iq3u7wtstrijneiuit525ctyjltj6vvupnzbla",
  "defined_tags": {
    "Oracle-Tags": {
      "CreatedBy": "oscemea001/jackie.boyle@oracle.com",
      "CreatedOn": "2023-01-12T19:52:34.839Z"
    },
    "osc": {
      "automatic_shutdown": "17:00_UTC",
      "automatic_startup": "07:00_UTC",
      "type": "user"
    },
    "osc_exacc": {
      "DB-Comments": "Used for: xxxx. Sys password: xxxxx",
      "scale_down_ocpus": "16",
      "scale_down_time": "no_autoscale",
      "scale_up_ocpus": "16",
      "scale_up_time": "no_autoscale"
    }
  },
  "display_name": "ecce-cl3",
  "freeform_tags": {},
  "identifier": "ocid1.compartment.oc1..aaaaaaaaoh7d6tqowvci2d66de45jnponj3sogek3rycjfuugigs2nuzm6la",
  "identity_context": {},
  "lifecycle_state": "ACTIVE",
  "resource_type": "Compartment",
  "search_context": null,
  "system_tags": {},
  "time_created": "2023-01-12T19:52:34.912000+00:00"
}, {
  "additional_details": {},
  "availability_domain": null,
  "compartment_id": "ocid1.compartment.oc1..aaaaaaaa2ak2x2y5tgpzm3iq3u7wtstrijneiuit525ctyjltj6vvupnzbla",
  "defined_tags": {
    "osc": {
      "automatic_shutdown": "17:00_UTC",
      "automatic_startup": "07:00_UTC",
      "created-by": "oscemea001/jackie.boyle@oracle.com\t",
      "date": "2020-08-05T15:49:30.108Z",
      "type": "user"
    }
  },
  "display_name": "ecce-cl1",
  "freeform_tags": {},
  "identifier": "ocid1.compartment.oc1..aaaaaaaassbyagwbymjd3oe6juk55hkfgzq5v2xkqlums5gxszxodtqvox2a",
  "identity_context": {},
  "lifecycle_state": "ACTIVE",
  "resource_type": "Compartment",
  "search_context": null,
  "system_tags": {},
  "time_created": "2020-08-05T15:49:30.169000+00:00"
}, {
  "additional_details": {},
  "availability_domain": null,
  "compartment_id": "ocid1.compartment.oc1..aaaaaaaa2ak2x2y5tgpzm3iq3u7wtstrijneiuit525ctyjltj6vvupnzbla",
  "defined_tags": {
    "Oracle-Tags": {
      "CreatedBy": "oscemea001/jackie.boyle@oracle.com",
      "CreatedOn": "2023-01-12T16:52:18.902Z"
    },
    "osc": {
      "automatic_shutdown": "17:00_UTC",
      "automatic_startup": "07:00_UTC",
      "type": "user"
    },
    "osc_exacc": {
      "DB-Comments": "Used for: xxxx. Sys password: xxxxx",
      "scale_down_ocpus": "16",
      "scale_down_time": "no_autoscale",
      "scale_up_ocpus": "16",
      "scale_up_time": "no_autoscale"
    }
  },
  "display_name": "ecce-cl2",
  "freeform_tags": {},
  "identifier": "ocid1.compartment.oc1..aaaaaaaajo5ccsj4jxibx7rrpjvqqorbxtznniu3ycgkzztcl2yipu5wyqhq",
  "identity_context": {},
  "lifecycle_state": "ACTIVE",
  "resource_type": "Compartment",
  "search_context": null,
  "system_tags": {},
  "time_created": "2023-01-12T16:52:18.960000+00:00"
}, {
  "additional_details": {},
  "availability_domain": null,
  "compartment_id": "ocid1.compartment.oc1..aaaaaaaa2ak2x2y5tgpzm3iq3u7wtstrijneiuit525ctyjltj6vvupnzbla",
  "defined_tags": {
    "Oracle-Tags": {
      "CreatedBy": "oscemea001/jackie.boyle@oracle.com",
      "CreatedOn": "2023-01-12T19:52:34.839Z"
    },
    "osc": {
      "automatic_shutdown": "17:00_UTC",
      "automatic_startup": "07:00_UTC",
      "type": "user"
    },
    "osc_exacc": {
      "DB-Comments": "Used for: xxxx. Sys password: xxxxx",
      "scale_down_ocpus": "16",
      "scale_down_time": "no_autoscale",
      "scale_up_ocpus": "16",
      "scale_up_time": "no_autoscale"
    }
  },
  "display_name": "ecce-cl3",
  "freeform_tags": {},
  "identifier": "ocid1.compartment.oc1..aaaaaaaaoh7d6tqowvci2d66de45jnponj3sogek3rycjfuugigs2nuzm6la",
  "identity_context": {},
  "lifecycle_state": "ACTIVE",
  "resource_type": "Compartment",
  "search_context": null,
  "system_tags": {},
  "time_created": "2023-01-12T19:52:34.912000+00:00"
}, {
  "additional_details": {},
  "availability_domain": null,
  "compartment_id": "ocid1.compartment.oc1..aaaaaaaa2ak2x2y5tgpzm3iq3u7wtstrijneiuit525ctyjltj6vvupnzbla",
  "defined_tags": {
    "osc": {
      "automatic_shutdown": "17:00_UTC",
      "automatic_startup": "07:00_UTC",
      "created-by": "oscemea001/jackie.boyle@oracle.com\t",
      "date": "2020-08-05T15:49:30.108Z",
      "type": "user"
    }
  },
  "display_name": "ecce-cl1",
  "freeform_tags": {},
  "identifier": "ocid1.compartment.oc1..aaaaaaaassbyagwbymjd3oe6juk55hkfgzq5v2xkqlums5gxszxodtqvox2a",
  "identity_context": {},
  "lifecycle_state": "ACTIVE",
  "resource_type": "Compartment",
  "search_context": null,
  "system_tags": {},
  "time_created": "2020-08-05T15:49:30.169000+00:00"
}, {
  "additional_details": {},
  "availability_domain": null,
  "compartment_id": "ocid1.compartment.oc1..aaaaaaaa2ak2x2y5tgpzm3iq3u7wtstrijneiuit525ctyjltj6vvupnzbla",
  "defined_tags": {
    "Oracle-Tags": {
      "CreatedBy": "oscemea001/jackie.boyle@oracle.com",
      "CreatedOn": "2023-01-12T16:52:18.902Z"
    },
    "osc": {
      "automatic_shutdown": "17:00_UTC",
      "automatic_startup": "07:00_UTC",
      "type": "user"
    },
    "osc_exacc": {
      "DB-Comments": "Used for: xxxx. Sys password: xxxxx",
      "scale_down_ocpus": "16",
      "scale_down_time": "no_autoscale",
      "scale_up_ocpus": "16",
      "scale_up_time": "no_autoscale"
    }
  },
  "display_name": "ecce-cl2",
  "freeform_tags": {},
  "identifier": "ocid1.compartment.oc1..aaaaaaaajo5ccsj4jxibx7rrpjvqqorbxtznniu3ycgkzztcl2yipu5wyqhq",
  "identity_context": {},
  "lifecycle_state": "ACTIVE",
  "resource_type": "Compartment",
  "search_context": null,
  "system_tags": {},
  "time_created": "2023-01-12T16:52:18.960000+00:00"
}, {
  "additional_details": {},
  "availability_domain": null,
  "compartment_id": "ocid1.compartment.oc1..aaaaaaaa2ak2x2y5tgpzm3iq3u7wtstrijneiuit525ctyjltj6vvupnzbla",
  "defined_tags": {
    "Oracle-Tags": {
      "CreatedBy": "oscemea001/jackie.boyle@oracle.com",
      "CreatedOn": "2023-01-12T19:52:34.839Z"
    },
    "osc": {
      "automatic_shutdown": "17:00_UTC",
      "automatic_startup": "07:00_UTC",
      "type": "user"
    },
    "osc_exacc": {
      "DB-Comments": "Used for: xxxx. Sys password: xxxxx",
      "scale_down_ocpus": "16",
      "scale_down_time": "no_autoscale",
      "scale_up_ocpus": "16",
      "scale_up_time": "no_autoscale"
    }
  },
  "display_name": "ecce-cl3",
  "freeform_tags": {},
  "identifier": "ocid1.compartment.oc1..aaaaaaaaoh7d6tqowvci2d66de45jnponj3sogek3rycjfuugigs2nuzm6la",
  "identity_context": {},
  "lifecycle_state": "ACTIVE",
  "resource_type": "Compartment",
  "search_context": null,
  "system_tags": {},
  "time_created": "2023-01-12T19:52:34.912000+00:00"
}, {
  "additional_details": {},
  "availability_domain": null,
  "compartment_id": "ocid1.compartment.oc1..aaaaaaaa2ak2x2y5tgpzm3iq3u7wtstrijneiuit525ctyjltj6vvupnzbla",
  "defined_tags": {},
  "display_name": "UA_1658563303826",
  "freeform_tags": {},
  "identifier": "ocid1.datasafeuserassessment.oc1.uk-london-1.abwgiljs2uptbg6e6rm6er4akouggplpggu7fcmpbkbiuhhttdlt7ucleska",
  "identity_context": {},
  "lifecycle_state": "SUCCEEDED",
  "resource_type": "DataSafeUserAssessment",
  "search_context": null,
  "system_tags": {},
  "time_created": "2022-07-23T08:01:43.832000+00:00"
}, {
  "additional_details": {},
  "availability_domain": null,
  "compartment_id": "ocid1.compartment.oc1..aaaaaaaa2ak2x2y5tgpzm3iq3u7wtstrijneiuit525ctyjltj6vvupnzbla",
  "defined_tags": {
    "osc": {
      "automatic_shutdown": "17:00_UTC",
      "automatic_startup": "07:00_UTC",
      "created-by": "oscemea001/jackie.boyle@oracle.com\t",
      "date": "2020-08-05T15:49:30.108Z",
      "type": "user"
    }
  },
  "display_name": "ecce-cl1",
  "freeform_tags": {},
  "identifier": "ocid1.compartment.oc1..aaaaaaaassbyagwbymjd3oe6juk55hkfgzq5v2xkqlums5gxszxodtqvox2a",
  "identity_context": {},
  "lifecycle_state": "ACTIVE",
  "resource_type": "Compartment",
  "search_context": null,
  "system_tags": {},
  "time_created": "2020-08-05T15:49:30.169000+00:00"
}, {
  "additional_details": {},
  "availability_domain": null,
  "compartment_id": "ocid1.compartment.oc1..aaaaaaaa2ak2x2y5tgpzm3iq3u7wtstrijneiuit525ctyjltj6vvupnzbla",
  "defined_tags": {
    "Oracle-Tags": {
      "CreatedBy": "oscemea001/jackie.boyle@oracle.com",
      "CreatedOn": "2023-01-12T16:52:18.902Z"
    },
    "osc": {
      "automatic_shutdown": "17:00_UTC",
      "automatic_startup": "07:00_UTC",
      "type": "user"
    },
    "osc_exacc": {
      "DB-Comments": "Used for: xxxx. Sys password: xxxxx",
      "scale_down_ocpus": "16",
      "scale_down_time": "no_autoscale",
      "scale_up_ocpus": "16",
      "scale_up_time": "no_autoscale"
    }
  },
  "display_name": "ecce-cl2",
  "freeform_tags": {},
  "identifier": "ocid1.compartment.oc1..aaaaaaaajo5ccsj4jxibx7rrpjvqqorbxtznniu3ycgkzztcl2yipu5wyqhq",
  "identity_context": {},
  "lifecycle_state": "ACTIVE",
  "resource_type": "Compartment",
  "search_context": null,
  "system_tags": {},
  "time_created": "2023-01-12T16:52:18.960000+00:00"
}, {
  "additional_details": {},
  "availability_domain": null,
  "compartment_id": "ocid1.compartment.oc1..aaaaaaaa2ak2x2y5tgpzm3iq3u7wtstrijneiuit525ctyjltj6vvupnzbla",
  "defined_tags": {
    "Oracle-Tags": {
      "CreatedBy": "oscemea001/jackie.boyle@oracle.com",
      "CreatedOn": "2023-01-12T19:52:34.839Z"
    },
    "osc": {
      "automatic_shutdown": "17:00_UTC",
      "automatic_startup": "07:00_UTC",
      "type": "user"
    },
    "osc_exacc": {
      "DB-Comments": "Used for: xxxx. Sys password: xxxxx",
      "scale_down_ocpus": "16",
      "scale_down_time": "no_autoscale",
      "scale_up_ocpus": "16",
      "scale_up_time": "no_autoscale"
    }
  },
  "display_name": "ecce-cl3",
  "freeform_tags": {},
  "identifier": "ocid1.compartment.oc1..aaaaaaaaoh7d6tqowvci2d66de45jnponj3sogek3rycjfuugigs2nuzm6la",
  "identity_context": {},
  "lifecycle_state": "ACTIVE",
  "resource_type": "Compartment",
  "search_context": null,
  "system_tags": {},
  "time_created": "2023-01-12T19:52:34.912000+00:00"
}, {
  "additional_details": {},
  "availability_domain": null,
  "compartment_id": "ocid1.compartment.oc1..aaaaaaaa2ak2x2y5tgpzm3iq3u7wtstrijneiuit525ctyjltj6vvupnzbla",
  "defined_tags": {
    "osc": {
      "automatic_shutdown": "17:00_UTC",
      "automatic_startup": "07:00_UTC",
      "created-by": "oscemea001/jackie.boyle@oracle.com\t",
      "date": "2020-08-05T15:49:30.108Z",
      "type": "user"
    }
  },
  "display_name": "ecce-cl1",
  "freeform_tags": {},
  "identifier": "ocid1.compartment.oc1..aaaaaaaassbyagwbymjd3oe6juk55hkfgzq5v2xkqlums5gxszxodtqvox2a",
  "identity_context": {},
  "lifecycle_state": "ACTIVE",
  "resource_type": "Compartment",
  "search_context": null,
  "system_tags": {},
  "time_created": "2020-08-05T15:49:30.169000+00:00"
}, {
  "additional_details": {},
  "availability_domain": null,
  "compartment_id": "ocid1.compartment.oc1..aaaaaaaa2ak2x2y5tgpzm3iq3u7wtstrijneiuit525ctyjltj6vvupnzbla",
  "defined_tags": {
    "Oracle-Tags": {
      "CreatedBy": "oscemea001/jackie.boyle@oracle.com",
      "CreatedOn": "2023-01-12T16:52:18.902Z"
    },
    "osc": {
      "automatic_shutdown": "17:00_UTC",
      "automatic_startup": "07:00_UTC",
      "type": "user"
    },
    "osc_exacc": {
      "DB-Comments": "Used for: xxxx. Sys password: xxxxx",
      "scale_down_ocpus": "16",
      "scale_down_time": "no_autoscale",
      "scale_up_ocpus": "16",
      "scale_up_time": "no_autoscale"
    }
  },
  "display_name": "ecce-cl2",
  "freeform_tags": {},
  "identifier": "ocid1.compartment.oc1..aaaaaaaajo5ccsj4jxibx7rrpjvqqorbxtznniu3ycgkzztcl2yipu5wyqhq",
  "identity_context": {},
  "lifecycle_state": "ACTIVE",
  "resource_type": "Compartment",
  "search_context": null,
  "system_tags": {},
  "time_created": "2023-01-12T16:52:18.960000+00:00"
}, {
  "additional_details": {},
  "availability_domain": null,
  "compartment_id": "ocid1.compartment.oc1..aaaaaaaa2ak2x2y5tgpzm3iq3u7wtstrijneiuit525ctyjltj6vvupnzbla",
  "defined_tags": {
    "Oracle-Tags": {
      "CreatedBy": "oscemea001/jackie.boyle@oracle.com",
      "CreatedOn": "2023-01-12T19:52:34.839Z"
    },
    "osc": {
      "automatic_shutdown": "17:00_UTC",
      "automatic_startup": "07:00_UTC",
      "type": "user"
    },
    "osc_exacc": {
      "DB-Comments": "Used for: xxxx. Sys password: xxxxx",
      "scale_down_ocpus": "16",
      "scale_down_time": "no_autoscale",
      "scale_up_ocpus": "16",
      "scale_up_time": "no_autoscale"
    }
  },
  "display_name": "ecce-cl3",
  "freeform_tags": {},
  "identifier": "ocid1.compartment.oc1..aaaaaaaaoh7d6tqowvci2d66de45jnponj3sogek3rycjfuugigs2nuzm6la",
  "identity_context": {},
  "lifecycle_state": "ACTIVE",
  "resource_type": "Compartment",
  "search_context": null,
  "system_tags": {},
  "time_created": "2023-01-12T19:52:34.912000+00:00"
}, {
  "additional_details": {},
  "availability_domain": null,
  "compartment_id": "ocid1.compartment.oc1..aaaaaaaa2ak2x2y5tgpzm3iq3u7wtstrijneiuit525ctyjltj6vvupnzbla",
  "defined_tags": {
    "osc": {
      "automatic_shutdown": "17:00_UTC",
      "automatic_startup": "07:00_UTC",
      "created-by": "oscemea001/jackie.boyle@oracle.com\t",
      "date": "2020-08-05T15:49:30.108Z",
      "type": "user"
    }
  },
  "display_name": "ecce-cl1",
  "freeform_tags": {},
  "identifier": "ocid1.compartment.oc1..aaaaaaaassbyagwbymjd3oe6juk55hkfgzq5v2xkqlums5gxszxodtqvox2a",
  "identity_context": {},
  "lifecycle_state": "ACTIVE",
  "resource_type": "Compartment",
  "search_context": null,
  "system_tags": {},
  "time_created": "2020-08-05T15:49:30.169000+00:00"
}, {
  "additional_details": {},
  "availability_domain": null,
  "compartment_id": "ocid1.compartment.oc1..aaaaaaaa2ak2x2y5tgpzm3iq3u7wtstrijneiuit525ctyjltj6vvupnzbla",
  "defined_tags": {
    "Oracle-Tags": {
      "CreatedBy": "oscemea001/jackie.boyle@oracle.com",
      "CreatedOn": "2023-01-12T16:52:18.902Z"
    },
    "osc": {
      "automatic_shutdown": "17:00_UTC",
      "automatic_startup": "07:00_UTC",
      "type": "user"
    },
    "osc_exacc": {
      "DB-Comments": "Used for: xxxx. Sys password: xxxxx",
      "scale_down_ocpus": "16",
      "scale_down_time": "no_autoscale",
      "scale_up_ocpus": "16",
      "scale_up_time": "no_autoscale"
    }
  },
  "display_name": "ecce-cl2",
  "freeform_tags": {},
  "identifier": "ocid1.compartment.oc1..aaaaaaaajo5ccsj4jxibx7rrpjvqqorbxtznniu3ycgkzztcl2yipu5wyqhq",
  "identity_context": {},
  "lifecycle_state": "ACTIVE",
  "resource_type": "Compartment",
  "search_context": null,
  "system_tags": {},
  "time_created": "2023-01-12T16:52:18.960000+00:00"
}, {
  "additional_details": {},
  "availability_domain": null,
  "compartment_id": "ocid1.compartment.oc1..aaaaaaaa2ak2x2y5tgpzm3iq3u7wtstrijneiuit525ctyjltj6vvupnzbla",
  "defined_tags": {
    "Oracle-Tags": {
      "CreatedBy": "oscemea001/jackie.boyle@oracle.com",
      "CreatedOn": "2023-01-12T19:52:34.839Z"
    },
    "osc": {
      "automatic_shutdown": "17:00_UTC",
      "automatic_startup": "07:00_UTC",
      "type": "user"
    },
    "osc_exacc": {
      "DB-Comments": "Used for: xxxx. Sys password: xxxxx",
      "scale_down_ocpus": "16",
      "scale_down_time": "no_autoscale",
      "scale_up_ocpus": "16",
      "scale_up_time": "no_autoscale"
    }
  },
  "display_name": "ecce-cl3",
  "freeform_tags": {},
  "identifier": "ocid1.compartment.oc1..aaaaaaaaoh7d6tqowvci2d66de45jnponj3sogek3rycjfuugigs2nuzm6la",
  "identity_context": {},
  "lifecycle_state": "ACTIVE",
  "resource_type": "Compartment",
  "search_context": null,
  "system_tags": {},
  "time_created": "2023-01-12T19:52:34.912000+00:00"
}, {
  "additional_details": {},
  "availability_domain": null,
  "compartment_id": "ocid1.compartment.oc1..aaaaaaaa2ak2x2y5tgpzm3iq3u7wtstrijneiuit525ctyjltj6vvupnzbla",
  "defined_tags": {
    "osc": {
      "automatic_shutdown": "17:00_UTC",
      "automatic_startup": "07:00_UTC",
      "created-by": "oscemea001/jackie.boyle@oracle.com\t",
      "date": "2020-08-05T15:49:30.108Z",
      "type": "user"
    }
  },
  "display_name": "ecce-cl1",
  "freeform_tags": {},
  "identifier": "ocid1.compartment.oc1..aaaaaaaassbyagwbymjd3oe6juk55hkfgzq5v2xkqlums5gxszxodtqvox2a",
  "identity_context": {},
  "lifecycle_state": "ACTIVE",
  "resource_type": "Compartment",
  "search_context": null,
  "system_tags": {},
  "time_created": "2020-08-05T15:49:30.169000+00:00"
}, {
  "additional_details": {},
  "availability_domain": null,
  "compartment_id": "ocid1.compartment.oc1..aaaaaaaa2ak2x2y5tgpzm3iq3u7wtstrijneiuit525ctyjltj6vvupnzbla",
  "defined_tags": {
    "Oracle-Tags": {
      "CreatedBy": "oscemea001/jackie.boyle@oracle.com",
      "CreatedOn": "2023-01-12T16:52:18.902Z"
    },
    "osc": {
      "automatic_shutdown": "17:00_UTC",
      "automatic_startup": "07:00_UTC",
      "type": "user"
    },
    "osc_exacc": {
      "DB-Comments": "Used for: xxxx. Sys password: xxxxx",
      "scale_down_ocpus": "16",
      "scale_down_time": "no_autoscale",
      "scale_up_ocpus": "16",
      "scale_up_time": "no_autoscale"
    }
  },
  "display_name": "ecce-cl2",
  "freeform_tags": {},
  "identifier": "ocid1.compartment.oc1..aaaaaaaajo5ccsj4jxibx7rrpjvqqorbxtznniu3ycgkzztcl2yipu5wyqhq",
  "identity_context": {},
  "lifecycle_state": "ACTIVE",
  "resource_type": "Compartment",
  "search_context": null,
  "system_tags": {},
  "time_created": "2023-01-12T16:52:18.960000+00:00"
}, {
  "additional_details": {},
  "availability_domain": null,
  "compartment_id": "ocid1.compartment.oc1..aaaaaaaa2ak2x2y5tgpzm3iq3u7wtstrijneiuit525ctyjltj6vvupnzbla",
  "defined_tags": {
    "Oracle-Tags": {
      "CreatedBy": "oscemea001/jackie.boyle@oracle.com",
      "CreatedOn": "2023-01-12T19:52:34.839Z"
    },
    "osc": {
      "automatic_shutdown": "17:00_UTC",
      "automatic_startup": "07:00_UTC",
      "type": "user"
    },
    "osc_exacc": {
      "DB-Comments": "Used for: xxxx. Sys password: xxxxx",
      "scale_down_ocpus": "16",
      "scale_down_time": "no_autoscale",
      "scale_up_ocpus": "16",
      "scale_up_time": "no_autoscale"
    }
  },
  "display_name": "ecce-cl3",
  "freeform_tags": {},
  "identifier": "ocid1.compartment.oc1..aaaaaaaaoh7d6tqowvci2d66de45jnponj3sogek3rycjfuugigs2nuzm6la",
  "identity_context": {},
  "lifecycle_state": "ACTIVE",
  "resource_type": "Compartment",
  "search_context": null,
  "system_tags": {},
  "time_created": "2023-01-12T19:52:34.912000+00:00"
}, {
  "additional_details": {},
  "availability_domain": null,
  "compartment_id": "ocid1.compartment.oc1..aaaaaaaa2ak2x2y5tgpzm3iq3u7wtstrijneiuit525ctyjltj6vvupnzbla",
  "defined_tags": {
    "osc": {
      "automatic_shutdown": "17:00_UTC",
      "automatic_startup": "07:00_UTC",
      "created-by": "oscemea001/jackie.boyle@oracle.com\t",
      "date": "2020-08-05T15:49:30.108Z",
      "type": "user"
    }
  },
  "display_name": "ecce-cl1",
  "freeform_tags": {},
  "identifier": "ocid1.compartment.oc1..aaaaaaaassbyagwbymjd3oe6juk55hkfgzq5v2xkqlums5gxszxodtqvox2a",
  "identity_context": {},
  "lifecycle_state": "ACTIVE",
  "resource_type": "Compartment",
  "search_context": null,
  "system_tags": {},
  "time_created": "2020-08-05T15:49:30.169000+00:00"
}, {
  "additional_details": {},
  "availability_domain": null,
  "compartment_id": "ocid1.compartment.oc1..aaaaaaaa2ak2x2y5tgpzm3iq3u7wtstrijneiuit525ctyjltj6vvupnzbla",
  "defined_tags": {
    "Oracle-Tags": {
      "CreatedBy": "oscemea001/jackie.boyle@oracle.com",
      "CreatedOn": "2023-01-12T16:52:18.902Z"
    },
    "osc": {
      "automatic_shutdown": "17:00_UTC",
      "automatic_startup": "07:00_UTC",
      "type": "user"
    },
    "osc_exacc": {
      "DB-Comments": "Used for: xxxx. Sys password: xxxxx",
      "scale_down_ocpus": "16",
      "scale_down_time": "no_autoscale",
      "scale_up_ocpus": "16",
      "scale_up_time": "no_autoscale"
    }
  },
  "display_name": "ecce-cl2",
  "freeform_tags": {},
  "identifier": "ocid1.compartment.oc1..aaaaaaaajo5ccsj4jxibx7rrpjvqqorbxtznniu3ycgkzztcl2yipu5wyqhq",
  "identity_context": {},
  "lifecycle_state": "ACTIVE",
  "resource_type": "Compartment",
  "search_context": null,
  "system_tags": {},
  "time_created": "2023-01-12T16:52:18.960000+00:00"
}, {
  "additional_details": {},
  "availability_domain": null,
  "compartment_id": "ocid1.compartment.oc1..aaaaaaaa2ak2x2y5tgpzm3iq3u7wtstrijneiuit525ctyjltj6vvupnzbla",
  "defined_tags": {
    "Oracle-Tags": {
      "CreatedBy": "oscemea001/jackie.boyle@oracle.com",
      "CreatedOn": "2023-01-12T19:52:34.839Z"
    },
    "osc": {
      "automatic_shutdown": "17:00_UTC",
      "automatic_startup": "07:00_UTC",
      "type": "user"
    },
    "osc_exacc": {
      "DB-Comments": "Used for: xxxx. Sys password: xxxxx",
      "scale_down_ocpus": "16",
      "scale_down_time": "no_autoscale",
      "scale_up_ocpus": "16",
      "scale_up_time": "no_autoscale"
    }
  },
  "display_name": "ecce-cl3",
  "freeform_tags": {},
  "identifier": "ocid1.compartment.oc1..aaaaaaaaoh7d6tqowvci2d66de45jnponj3sogek3rycjfuugigs2nuzm6la",
  "identity_context": {},
  "lifecycle_state": "ACTIVE",
  "resource_type": "Compartment",
  "search_context": null,
  "system_tags": {},
  "time_created": "2023-01-12T19:52:34.912000+00:00"
}, {
  "additional_details": {},
  "availability_domain": null,
  "compartment_id": "ocid1.compartment.oc1..aaaaaaaa2ak2x2y5tgpzm3iq3u7wtstrijneiuit525ctyjltj6vvupnzbla",
  "defined_tags": {
    "osc": {
      "automatic_shutdown": "17:00_UTC",
      "automatic_startup": "07:00_UTC",
      "created-by": "oscemea001/jackie.boyle@oracle.com\t",
      "date": "2020-08-05T15:49:30.108Z",
      "type": "user"
    }
  },
  "display_name": "ecce-cl1",
  "freeform_tags": {},
  "identifier": "ocid1.compartment.oc1..aaaaaaaassbyagwbymjd3oe6juk55hkfgzq5v2xkqlums5gxszxodtqvox2a",
  "identity_context": {},
  "lifecycle_state": "ACTIVE",
  "resource_type": "Compartment",
  "search_context": null,
  "system_tags": {},
  "time_created": "2020-08-05T15:49:30.169000+00:00"
}, {
  "additional_details": {},
  "availability_domain": null,
  "compartment_id": "ocid1.compartment.oc1..aaaaaaaa2ak2x2y5tgpzm3iq3u7wtstrijneiuit525ctyjltj6vvupnzbla",
  "defined_tags": {
    "Oracle-Tags": {
      "CreatedBy": "oscemea001/jackie.boyle@oracle.com",
      "CreatedOn": "2023-01-12T16:52:18.902Z"
    },
    "osc": {
      "automatic_shutdown": "17:00_UTC",
      "automatic_startup": "07:00_UTC",
      "type": "user"
    },
    "osc_exacc": {
      "DB-Comments": "Used for: xxxx. Sys password: xxxxx",
      "scale_down_ocpus": "16",
      "scale_down_time": "no_autoscale",
      "scale_up_ocpus": "16",
      "scale_up_time": "no_autoscale"
    }
  },
  "display_name": "ecce-cl2",
  "freeform_tags": {},
  "identifier": "ocid1.compartment.oc1..aaaaaaaajo5ccsj4jxibx7rrpjvqqorbxtznniu3ycgkzztcl2yipu5wyqhq",
  "identity_context": {},
  "lifecycle_state": "ACTIVE",
  "resource_type": "Compartment",
  "search_context": null,
  "system_tags": {},
  "time_created": "2023-01-12T16:52:18.960000+00:00"
}, {
  "additional_details": {},
  "availability_domain": null,
  "compartment_id": "ocid1.compartment.oc1..aaaaaaaa2ak2x2y5tgpzm3iq3u7wtstrijneiuit525ctyjltj6vvupnzbla",
  "defined_tags": {
    "Oracle-Tags": {
      "CreatedBy": "oscemea001/jackie.boyle@oracle.com",
      "CreatedOn": "2023-01-12T19:52:34.839Z"
    },
    "osc": {
      "automatic_shutdown": "17:00_UTC",
      "automatic_startup": "07:00_UTC",
      "type": "user"
    },
    "osc_exacc": {
      "DB-Comments": "Used for: xxxx. Sys password: xxxxx",
      "scale_down_ocpus": "16",
      "scale_down_time": "no_autoscale",
      "scale_up_ocpus": "16",
      "scale_up_time": "no_autoscale"
    }
  },
  "display_name": "ecce-cl3",
  "freeform_tags": {},
  "identifier": "ocid1.compartment.oc1..aaaaaaaaoh7d6tqowvci2d66de45jnponj3sogek3rycjfuugigs2nuzm6la",
  "identity_context": {},
  "lifecycle_state": "ACTIVE",
  "resource_type": "Compartment",
  "search_context": null,
  "system_tags": {},
  "time_created": "2023-01-12T19:52:34.912000+00:00"
}, {
  "additional_details": {},
  "availability_domain": null,
  "compartment_id": "ocid1.compartment.oc1..aaaaaaaa2ak2x2y5tgpzm3iq3u7wtstrijneiuit525ctyjltj6vvupnzbla",
  "defined_tags": {
    "osc": {
      "automatic_shutdown": "17:00_UTC",
      "automatic_startup": "07:00_UTC",
      "created-by": "oscemea001/jackie.boyle@oracle.com\t",
      "date": "2020-08-05T15:49:30.108Z",
      "type": "user"
    }
  },
  "display_name": "ecce-cl1",
  "freeform_tags": {},
  "identifier": "ocid1.compartment.oc1..aaaaaaaassbyagwbymjd3oe6juk55hkfgzq5v2xkqlums5gxszxodtqvox2a",
  "identity_context": {},
  "lifecycle_state": "ACTIVE",
  "resource_type": "Compartment",
  "search_context": null,
  "system_tags": {},
  "time_created": "2020-08-05T15:49:30.169000+00:00"
}, {
  "additional_details": {},
  "availability_domain": null,
  "compartment_id": "ocid1.compartment.oc1..aaaaaaaa2ak2x2y5tgpzm3iq3u7wtstrijneiuit525ctyjltj6vvupnzbla",
  "defined_tags": {
    "Oracle-Tags": {
      "CreatedBy": "oscemea001/jackie.boyle@oracle.com",
      "CreatedOn": "2023-01-12T16:52:18.902Z"
    },
    "osc": {
      "automatic_shutdown": "17:00_UTC",
      "automatic_startup": "07:00_UTC",
      "type": "user"
    },
    "osc_exacc": {
      "DB-Comments": "Used for: xxxx. Sys password: xxxxx",
      "scale_down_ocpus": "16",
      "scale_down_time": "no_autoscale",
      "scale_up_ocpus": "16",
      "scale_up_time": "no_autoscale"
    }
  },
  "display_name": "ecce-cl2",
  "freeform_tags": {},
  "identifier": "ocid1.compartment.oc1..aaaaaaaajo5ccsj4jxibx7rrpjvqqorbxtznniu3ycgkzztcl2yipu5wyqhq",
  "identity_context": {},
  "lifecycle_state": "ACTIVE",
  "resource_type": "Compartment",
  "search_context": null,
  "system_tags": {},
  "time_created": "2023-01-12T16:52:18.960000+00:00"
}, {
  "additional_details": {},
  "availability_domain": null,
  "compartment_id": "ocid1.compartment.oc1..aaaaaaaa2ak2x2y5tgpzm3iq3u7wtstrijneiuit525ctyjltj6vvupnzbla",
  "defined_tags": {
    "Oracle-Tags": {
      "CreatedBy": "oscemea001/jackie.boyle@oracle.com",
      "CreatedOn": "2023-01-12T19:52:34.839Z"
    },
    "osc": {
      "automatic_shutdown": "17:00_UTC",
      "automatic_startup": "07:00_UTC",
      "type": "user"
    },
    "osc_exacc": {
      "DB-Comments": "Used for: xxxx. Sys password: xxxxx",
      "scale_down_ocpus": "16",
      "scale_down_time": "no_autoscale",
      "scale_up_ocpus": "16",
      "scale_up_time": "no_autoscale"
    }
  },
  "display_name": "ecce-cl3",
  "freeform_tags": {},
  "identifier": "ocid1.compartment.oc1..aaaaaaaaoh7d6tqowvci2d66de45jnponj3sogek3rycjfuugigs2nuzm6la",
  "identity_context": {},
  "lifecycle_state": "ACTIVE",
  "resource_type": "Compartment",
  "search_context": null,
  "system_tags": {},
  "time_created": "2023-01-12T19:52:34.912000+00:00"
}, {
  "additional_details": {},
  "availability_domain": null,
  "compartment_id": "ocid1.compartment.oc1..aaaaaaaa2ak2x2y5tgpzm3iq3u7wtstrijneiuit525ctyjltj6vvupnzbla",
  "defined_tags": {
    "osc": {
      "automatic_shutdown": "17:00_UTC",
      "automatic_startup": "07:00_UTC",
      "created-by": "oscemea001/jackie.boyle@oracle.com\t",
      "date": "2020-08-05T15:49:30.108Z",
      "type": "user"
    }
  },
  "display_name": "ecce-cl1",
  "freeform_tags": {},
  "identifier": "ocid1.compartment.oc1..aaaaaaaassbyagwbymjd3oe6juk55hkfgzq5v2xkqlums5gxszxodtqvox2a",
  "identity_context": {},
  "lifecycle_state": "ACTIVE",
  "resource_type": "Compartment",
  "search_context": null,
  "system_tags": {},
  "time_created": "2020-08-05T15:49:30.169000+00:00"
}, {
  "additional_details": {},
  "availability_domain": null,
  "compartment_id": "ocid1.compartment.oc1..aaaaaaaa2ak2x2y5tgpzm3iq3u7wtstrijneiuit525ctyjltj6vvupnzbla",
  "defined_tags": {
    "Oracle-Tags": {
      "CreatedBy": "oscemea001/jackie.boyle@oracle.com",
      "CreatedOn": "2023-01-12T16:52:18.902Z"
    },
    "osc": {
      "automatic_shutdown": "17:00_UTC",
      "automatic_startup": "07:00_UTC",
      "type": "user"
    },
    "osc_exacc": {
      "DB-Comments": "Used for: xxxx. Sys password: xxxxx",
      "scale_down_ocpus": "16",
      "scale_down_time": "no_autoscale",
      "scale_up_ocpus": "16",
      "scale_up_time": "no_autoscale"
    }
  },
  "display_name": "ecce-cl2",
  "freeform_tags": {},
  "identifier": "ocid1.compartment.oc1..aaaaaaaajo5ccsj4jxibx7rrpjvqqorbxtznniu3ycgkzztcl2yipu5wyqhq",
  "identity_context": {},
  "lifecycle_state": "ACTIVE",
  "resource_type": "Compartment",
  "search_context": null,
  "system_tags": {},
  "time_created": "2023-01-12T16:52:18.960000+00:00"
}, {
  "additional_details": {},
  "availability_domain": null,
  "compartment_id": "ocid1.compartment.oc1..aaaaaaaa2ak2x2y5tgpzm3iq3u7wtstrijneiuit525ctyjltj6vvupnzbla",
  "defined_tags": {
    "Oracle-Tags": {
      "CreatedBy": "oscemea001/jackie.boyle@oracle.com",
      "CreatedOn": "2023-01-12T19:52:34.839Z"
    },
    "osc": {
      "automatic_shutdown": "17:00_UTC",
      "automatic_startup": "07:00_UTC",
      "type": "user"
    },
    "osc_exacc": {
      "DB-Comments": "Used for: xxxx. Sys password: xxxxx",
      "scale_down_ocpus": "16",
      "scale_down_time": "no_autoscale",
      "scale_up_ocpus": "16",
      "scale_up_time": "no_autoscale"
    }
  },
  "display_name": "ecce-cl3",
  "freeform_tags": {},
  "identifier": "ocid1.compartment.oc1..aaaaaaaaoh7d6tqowvci2d66de45jnponj3sogek3rycjfuugigs2nuzm6la",
  "identity_context": {},
  "lifecycle_state": "ACTIVE",
  "resource_type": "Compartment",
  "search_context": null,
  "system_tags": {},
  "time_created": "2023-01-12T19:52:34.912000+00:00"
}]