[{
  "additional_details": {},
  "availability_domain": null,
  "compartment_id": "ocid1.compartment.oc1..aaaaaaaaywyv2yjkotrt3ppnaa6cw2suyrkacyegeuzinricrvcer6ulynza",
  "defined_tags": {},
  "display_name": "SA_1654854987710",
  "freeform_tags": {},
  "identifier": "ocid1.datasafesecurityassessment.oc1.eu-frankfurt-1.abtheljtetygcqn6hmvlgfkgz7vyugbaapbf77t67o2za6khd2xzxmc7ytvq",
  "identity_context": {},
  "lifecycle_state": "SUCCEEDED",
  "resource_type": "DataSafeSecurityAssessment",
  "search_context": null,
  "system_tags": {},
  "time_created": "2022-06-10T09:56:27.713000+00:00"
}, {
  "additional_details": {},
  "availability_domain": null,
  "compartment_id": "ocid1.compartment.oc1..aaaaaaaaywyv2yjkotrt3ppnaa6cw2suyrkacyegeuzinricrvcer6ulynza",
  "defined_tags": {},
  "display_name": "UA_1654856294166",
  "freeform_tags": {},
  "identifier": "ocid1.datasafeuserassessment.oc1.eu-frankfurt-1.abtheljt6wsfozpci6w5dgadu5ic2xtn2kv3wu4sc4jo7unldh24siqmzx7a",
  "identity_context": {},
  "lifecycle_state": "SUCCEEDED",
  "resource_type": "DataSafeUserAssessment",
  "search_context": null,
  "system_tags": {},
  "time_created": "2022-06-10T10:18:14.169000+00:00"
}, {
  "additional_details": {},
  "availability_domain": null,
  "compartment_id": "ocid1.compartment.oc1..aaaaaaaaywyv2yjkotrt3ppnaa6cw2suyrkacyegeuzinricrvcer6ulynza",
  "defined_tags": {},
  "display_name": "logging_analytics_automatic_key",
  "freeform_tags": {},
  "identifier": "ocid1.managementagentinstallkey.oc1.eu-frankfurt-1.amaaaaaanmvrbeaavsnt7wao6mhaqzrxgo3n6lcb5pprjkfneedbmcerdoqq",
  "identity_context": {},
  "lifecycle_state": "Active",
  "resource_type": "ManagementAgentInstallKey",
  "search_context": null,
  "system_tags": {},
  "time_created": "2023-11-16T21:23:53.621000+00:00"
}, {
  "additional_details": {},
  "availability_domain": null,
  "compartment_id": "ocid1.compartment.oc1..aaaaaaaaywyv2yjkotrt3ppnaa6cw2suyrkacyegeuzinricrvcer6ulynza",
  "defined_tags": {},
  "display_name": "SA_1654913457269",
  "freeform_tags": {},
  "identifier": "ocid1.datasafesecurityassessment.oc1.iad.abuwcljsyvqly75cind27m6tnep4ewqnr63xapopimuwwdngoivnmfewbaqq",
  "identity_context": {},
  "lifecycle_state": "SUCCEEDED",
  "resource_type": "DataSafeSecurityAssessment",
  "search_context": null,
  "system_tags": {},
  "time_created": "2022-06-11T02:10:57.273000+00:00"
}, {
  "additional_details": {},
  "availability_domain": null,
  "compartment_id": "ocid1.compartment.oc1..aaaaaaaaywyv2yjkotrt3ppnaa6cw2suyrkacyegeuzinricrvcer6ulynza",
  "defined_tags": {},
  "display_name": "UA_1654907528596",
  "freeform_tags": {},
  "identifier": "ocid1.datasafeuserassessment.oc1.iad.abuwcljtmmrzowybk4jgaklmzurexwcmewyos2u2gqtqyjhy4dkack66vwva",
  "identity_context": {},
  "lifecycle_state": "SUCCEEDED",
  "resource_type": "DataSafeUserAssessment",
  "search_context": null,
  "system_tags": {},
  "time_created": "2022-06-11T00:32:08.608000+00:00"
}, {
  "additional_details": {},
  "availability_domain": null,
  "compartment_id": "ocid1.compartment.oc1..aaaaaaaaywyv2yjkotrt3ppnaa6cw2suyrkacyegeuzinricrvcer6ulynza",
  "defined_tags": {},
  "display_name": "UA_1658563239669",
  "freeform_tags": {},
  "identifier": "ocid1.datasafeuserassessment.oc1.uk-london-1.abwgiljr46pxmhf2ke7qnczh2jj6scjqtg77dvega4cpksofult3sttqgkxa",
  "identity_context": {},
  "lifecycle_state": "SUCCEEDED",
  "resource_type": "DataSafeUserAssessment",
  "search_context": null,
  "system_tags": {},
  "time_created": "2022-07-23T08:00:39.675000+00:00"
}]