[{
  "additional_details": {},
  "availability_domain": null,
  "compartment_id": "ocid1.compartment.oc1..aaaaaaaa7dqjira7dmi5yf56h2673nrcltmrikwgp6qbocy256hnzbroz4da",
  "defined_tags": {},
  "display_name": "SA_1654854947016",
  "freeform_tags": {},
  "identifier": "ocid1.datasafesecurityassessment.oc1.eu-frankfurt-1.abtheljrpxiyqqluh3j4t5wvrj2pstucmzcx567eedlwn72plrhjuf74kxmq",
  "identity_context": {},
  "lifecycle_state": "SUCCEEDED",
  "resource_type": "DataSafeSecurityAssessment",
  "search_context": null,
  "system_tags": {},
  "time_created": "2022-06-10T09:55:47.029000+00:00"
}, {
  "additional_details": {},
  "availability_domain": null,
  "compartment_id": "ocid1.compartment.oc1..aaaaaaaa7dqjira7dmi5yf56h2673nrcltmrikwgp6qbocy256hnzbroz4da",
  "defined_tags": {},
  "display_name": "UA_1654856257812",
  "freeform_tags": {},
  "identifier": "ocid1.datasafeuserassessment.oc1.eu-frankfurt-1.abtheljssky72oj2audzy2jubbkxh6cvvhpru5gmmjbtoq5udk6xwpnfegra",
  "identity_context": {},
  "lifecycle_state": "SUCCEEDED",
  "resource_type": "DataSafeUserAssessment",
  "search_context": null,
  "system_tags": {},
  "time_created": "2022-06-10T10:17:37.816000+00:00"
}, {
  "additional_details": {},
  "availability_domain": null,
  "compartment_id": "ocid1.compartment.oc1..aaaaaaaa7dqjira7dmi5yf56h2673nrcltmrikwgp6qbocy256hnzbroz4da",
  "defined_tags": {},
  "display_name": "SA_1654913414515",
  "freeform_tags": {},
  "identifier": "ocid1.datasafesecurityassessment.oc1.iad.abuwcljs6sbv7vbsxpupna2pneocpsrwozmldxzt37segpszjwkjuuidkeeq",
  "identity_context": {},
  "lifecycle_state": "SUCCEEDED",
  "resource_type": "DataSafeSecurityAssessment",
  "search_context": null,
  "system_tags": {},
  "time_created": "2022-06-11T02:10:14.522000+00:00"
}, {
  "additional_details": {},
  "availability_domain": null,
  "compartment_id": "ocid1.compartment.oc1..aaaaaaaa7dqjira7dmi5yf56h2673nrcltmrikwgp6qbocy256hnzbroz4da",
  "defined_tags": {},
  "display_name": "UA_1654907498106",
  "freeform_tags": {},
  "identifier": "ocid1.datasafeuserassessment.oc1.iad.abuwcljtd22yx3gyxjsf2mnfk5do2gxjbrrihulxp232mpbmdoqa5edmzuoq",
  "identity_context": {},
  "lifecycle_state": "SUCCEEDED",
  "resource_type": "DataSafeUserAssessment",
  "search_context": null,
  "system_tags": {},
  "time_created": "2022-06-11T00:31:38.113000+00:00"
}, {
  "additional_details": {},
  "availability_domain": null,
  "compartment_id": "ocid1.compartment.oc1..aaaaaaaa7dqjira7dmi5yf56h2673nrcltmrikwgp6qbocy256hnzbroz4da",
  "defined_tags": {},
  "display_name": "UA_1658563209113",
  "freeform_tags": {},
  "identifier": "ocid1.datasafeuserassessment.oc1.uk-london-1.abwgiljsuxt2sp53hzio7xx5mku52o4p4nzddl33fhjw5x3wawx5cmkc7ova",
  "identity_context": {},
  "lifecycle_state": "SUCCEEDED",
  "resource_type": "DataSafeUserAssessment",
  "search_context": null,
  "system_tags": {},
  "time_created": "2022-07-23T08:00:09.135000+00:00"
}]