[{
  "additional_details": {},
  "availability_domain": null,
  "compartment_id": "ocid1.compartment.oc1..aaaaaaaapg6e3ceqxkmh27oeupg735l6k5nc2fcmq67l7pz3llebyhpkvlva",
  "defined_tags": {
    "Oracle-Tags": {
      "CreatedBy": "oscemea001/eric.vinck@oracle.com",
      "CreatedOn": "2021-07-12T16:25:32.061Z"
    },
    "osc": {
      "automatic_shutdown": "17:00_UTC",
      "automatic_startup": "07:00_UTC",
      "type": "user"
    }
  },
  "display_name": "0.10.in-addr.arpa",
  "freeform_tags": {},
  "identifier": "ocid1.dns-zone.oc1.eu-frankfurt-1.aaaaaaaar66d726jn3ohjgkrcbfpbv2rvkag2zqyrvvnl3cf3fjtrbmxqrla",
  "identity_context": {},
  "lifecycle_state": "ACTIVE",
  "resource_type": "CustomerDnsZone",
  "search_context": null,
  "system_tags": {},
  "time_created": "2021-07-12T16:25:33.601000+00:00"
}, {
  "additional_details": {},
  "availability_domain": null,
  "compartment_id": "ocid1.compartment.oc1..aaaaaaaapg6e3ceqxkmh27oeupg735l6k5nc2fcmq67l7pz3llebyhpkvlva",
  "defined_tags": {
    "Oracle-Tags": {
      "CreatedBy": "oscemea001/eric.vinck@oracle.com",
      "CreatedOn": "2021-07-12T16:25:32.061Z"
    },
    "osc": {
      "automatic_shutdown": "17:00_UTC",
      "automatic_startup": "07:00_UTC",
      "type": "user"
    }
  },
  "display_name": "Default DHCP Options for vcn-20210712-1820",
  "freeform_tags": {},
  "identifier": "ocid1.dhcpoptions.oc1.eu-frankfurt-1.aaaaaaaaouz5gbrinhe4jqfsk4377idu2lm72zwwmin2jr747c5ug4srew5a",
  "identity_context": {},
  "lifecycle_state": "AVAILABLE",
  "resource_type": "DHCPOptions",
  "search_context": null,
  "system_tags": {},
  "time_created": "2021-07-12T16:25:32.416000+00:00"
}, {
  "additional_details": {},
  "availability_domain": null,
  "compartment_id": "ocid1.compartment.oc1..aaaaaaaapg6e3ceqxkmh27oeupg735l6k5nc2fcmq67l7pz3llebyhpkvlva",
  "defined_tags": {
    "Oracle-Tags": {
      "CreatedBy": "oscemea001/eric.vinck@oracle.com",
      "CreatedOn": "2021-07-12T16:25:32.061Z"
    },
    "osc": {
      "automatic_shutdown": "17:00_UTC",
      "automatic_startup": "07:00_UTC",
      "type": "user"
    }
  },
  "display_name": "Default Route Table for vcn-20210712-1820",
  "freeform_tags": {},
  "identifier": "ocid1.routetable.oc1.eu-frankfurt-1.aaaaaaaahnafvoggavlmp3fqz3zf36m7wd364qqundksw7wxn3xank6tcxqa",
  "identity_context": {},
  "lifecycle_state": "AVAILABLE",
  "resource_type": "RouteTable",
  "search_context": null,
  "system_tags": {},
  "time_created": "2021-07-12T16:25:32.187000+00:00"
}, {
  "additional_details": {},
  "availability_domain": null,
  "compartment_id": "ocid1.compartment.oc1..aaaaaaaapg6e3ceqxkmh27oeupg735l6k5nc2fcmq67l7pz3llebyhpkvlva",
  "defined_tags": {
    "Oracle-Tags": {
      "CreatedBy": "oscemea001/eric.vinck@oracle.com",
      "CreatedOn": "2021-07-12T16:25:32.061Z"
    },
    "osc": {
      "automatic_shutdown": "17:00_UTC",
      "automatic_startup": "07:00_UTC",
      "type": "user"
    }
  },
  "display_name": "Default Security List for vcn-20210712-1820",
  "freeform_tags": {},
  "identifier": "ocid1.securitylist.oc1.eu-frankfurt-1.aaaaaaaar64jhbm3sswimmn4ww2jbfpfyuin3t6xp7hzl2rjenrbuaxh42ja",
  "identity_context": {},
  "lifecycle_state": "AVAILABLE",
  "resource_type": "SecurityList",
  "search_context": null,
  "system_tags": {},
  "time_created": "2021-07-12T16:25:32.187000+00:00"
}, {
  "additional_details": {},
  "availability_domain": null,
  "compartment_id": "ocid1.compartment.oc1..aaaaaaaapg6e3ceqxkmh27oeupg735l6k5nc2fcmq67l7pz3llebyhpkvlva",
  "defined_tags": {
    "Oracle-Tags": {
      "CreatedBy": "oscemea001/eric.vinck@oracle.com",
      "CreatedOn": "2021-07-12T16:25:33.008Z"
    },
    "osc": {
      "automatic_shutdown": "17:00_UTC",
      "automatic_startup": "07:00_UTC",
      "type": "user"
    }
  },
  "display_name": "Internet Gateway vcn-20210712-1820",
  "freeform_tags": {},
  "identifier": "ocid1.internetgateway.oc1.eu-frankfurt-1.aaaaaaaabrvstidbqdi7lhxfhy3xaznodoicvpxfc3guzqwzb7dxml6fqnxq",
  "identity_context": {},
  "lifecycle_state": "AVAILABLE",
  "resource_type": "InternetGateway",
  "search_context": null,
  "system_tags": {},
  "time_created": "2021-07-12T16:25:33.053000+00:00"
}, {
  "additional_details": {},
  "availability_domain": null,
  "compartment_id": "ocid1.compartment.oc1..aaaaaaaapg6e3ceqxkmh27oeupg735l6k5nc2fcmq67l7pz3llebyhpkvlva",
  "defined_tags": {},
  "display_name": "SA_1654855037689",
  "freeform_tags": {},
  "identifier": "ocid1.datasafesecurityassessment.oc1.eu-frankfurt-1.abtheljspwuid7wkasfh6dqmvuhlyezvggr6skdoovu55nq5ngs66uq32p2a",
  "identity_context": {},
  "lifecycle_state": "SUCCEEDED",
  "resource_type": "DataSafeSecurityAssessment",
  "search_context": null,
  "system_tags": {},
  "time_created": "2022-06-10T09:57:17.694000+00:00"
}, {
  "additional_details": {},
  "availability_domain": null,
  "compartment_id": "ocid1.compartment.oc1..aaaaaaaapg6e3ceqxkmh27oeupg735l6k5nc2fcmq67l7pz3llebyhpkvlva",
  "defined_tags": {},
  "display_name": "UA_1654856348828",
  "freeform_tags": {},
  "identifier": "ocid1.datasafeuserassessment.oc1.eu-frankfurt-1.abtheljrsirau5b62fanrj3fwmvfmvhkij6r3isobkzgmdupibi4llrgr55q",
  "identity_context": {},
  "lifecycle_state": "SUCCEEDED",
  "resource_type": "DataSafeUserAssessment",
  "search_context": null,
  "system_tags": {},
  "time_created": "2022-06-10T10:19:08.831000+00:00"
}, {
  "additional_details": {},
  "availability_domain": "",
  "compartment_id": "ocid1.compartment.oc1..aaaaaaaapg6e3ceqxkmh27oeupg735l6k5nc2fcmq67l7pz3llebyhpkvlva",
  "defined_tags": {
    "Oracle-Tags": {
      "CreatedBy": "oscemea001/eric.vinck@oracle.com",
      "CreatedOn": "2021-07-07T08:25:48.501Z"
    },
    "osc": {
      "automatic_shutdown": "17:00_UTC",
      "automatic_startup": "07:00_UTC",
      "type": "user"
    }
  },
  "display_name": "code",
  "freeform_tags": {},
  "identifier": "ocid1.bucket.oc1.eu-frankfurt-1.aaaaaaaaqghyj6envcwyksjr2nnmwblschdp5qcfcjquk5rfjom2mvzflgna",
  "identity_context": {},
  "lifecycle_state": "active",
  "resource_type": "Bucket",
  "search_context": null,
  "system_tags": {},
  "time_created": "2021-07-07T08:25:48.516000+00:00"
}, {
  "additional_details": {},
  "availability_domain": null,
  "compartment_id": "ocid1.compartment.oc1..aaaaaaaapg6e3ceqxkmh27oeupg735l6k5nc2fcmq67l7pz3llebyhpkvlva",
  "defined_tags": {},
  "display_name": "code",
  "freeform_tags": {},
  "identifier": "ocid1.loganalyticsentity.oc1.eu-frankfurt-1.amaaaaaanmvrbeaavdyzxpzltakk3ru2pi7tt6kkc7vjb2axxpb5q5cf4otq",
  "identity_context": {},
  "lifecycle_state": "Active",
  "resource_type": "LogAnalyticsEntity",
  "search_context": null,
  "system_tags": {},
  "time_created": "2021-12-17T09:43:53.672000+00:00"
}, {
  "additional_details": {},
  "availability_domain": "",
  "compartment_id": "ocid1.compartment.oc1..aaaaaaaapg6e3ceqxkmh27oeupg735l6k5nc2fcmq67l7pz3llebyhpkvlva",
  "defined_tags": {
    "Oracle-Tags": {
      "CreatedBy": "oscemea001/eric.vinck@oracle.com",
      "CreatedOn": "2021-07-07T14:23:36.404Z"
    },
    "osc": {
      "automatic_shutdown": "17:00_UTC",
      "automatic_startup": "07:00_UTC",
      "type": "user"
    }
  },
  "display_name": "data",
  "freeform_tags": {},
  "identifier": "ocid1.bucket.oc1.eu-frankfurt-1.aaaaaaaaqfufept5kwfq3fepwsqka45m3d3o6ntccow6y5xjohb5y4yx3xvq",
  "identity_context": {},
  "lifecycle_state": "active",
  "resource_type": "Bucket",
  "search_context": null,
  "system_tags": {},
  "time_created": "2021-07-07T14:23:36.430000+00:00"
}, {
  "additional_details": {},
  "availability_domain": null,
  "compartment_id": "ocid1.compartment.oc1..aaaaaaaapg6e3ceqxkmh27oeupg735l6k5nc2fcmq67l7pz3llebyhpkvlva",
  "defined_tags": {},
  "display_name": "data",
  "freeform_tags": {},
  "identifier": "ocid1.loganalyticsentity.oc1.eu-frankfurt-1.amaaaaaanmvrbeaazvq4t56prtlmnsqg5sffvas7fbvfqksn4wvcpvswtosa",
  "identity_context": {},
  "lifecycle_state": "Active",
  "resource_type": "LogAnalyticsEntity",
  "search_context": null,
  "system_tags": {},
  "time_created": "2021-12-17T09:43:14.810000+00:00"
}, {
  "additional_details": {},
  "availability_domain": "",
  "compartment_id": "ocid1.compartment.oc1..aaaaaaaapg6e3ceqxkmh27oeupg735l6k5nc2fcmq67l7pz3llebyhpkvlva",
  "defined_tags": {
    "Oracle-Tags": {
      "CreatedBy": "oscemea001/eric.vinck@oracle.com",
      "CreatedOn": "2021-08-20T15:29:35.883Z"
    },
    "osc": {
      "automatic_shutdown": "17:00_UTC",
      "automatic_startup": "07:00_UTC",
      "type": "user"
    }
  },
  "display_name": "data2",
  "freeform_tags": {},
  "identifier": "ocid1.bucket.oc1.eu-frankfurt-1.aaaaaaaaiaz57ewozwl4jcvyiyornya3sm4bccap6zyynfe5iyfsiyomocaq",
  "identity_context": {},
  "lifecycle_state": "active",
  "resource_type": "Bucket",
  "search_context": null,
  "system_tags": {},
  "time_created": "2021-08-20T15:29:35.907000+00:00"
}, {
  "additional_details": {},
  "availability_domain": null,
  "compartment_id": "ocid1.compartment.oc1..aaaaaaaapg6e3ceqxkmh27oeupg735l6k5nc2fcmq67l7pz3llebyhpkvlva",
  "defined_tags": {},
  "display_name": "data2",
  "freeform_tags": {},
  "identifier": "ocid1.loganalyticsentity.oc1.eu-frankfurt-1.amaaaaaanmvrbeaamyo6hygadjeyq5m4bl3bafnfnq6a5al7fmknp5hdhtfa",
  "identity_context": {},
  "lifecycle_state": "Active",
  "resource_type": "LogAnalyticsEntity",
  "search_context": null,
  "system_tags": {},
  "time_created": "2021-12-17T09:43:53.902000+00:00"
}, {
  "additional_details": {},
  "availability_domain": null,
  "compartment_id": "ocid1.compartment.oc1..aaaaaaaapg6e3ceqxkmh27oeupg735l6k5nc2fcmq67l7pz3llebyhpkvlva",
  "defined_tags": {},
  "display_name": "ext-tables",
  "freeform_tags": {},
  "identifier": "ocid1.loganalyticsentity.oc1.eu-frankfurt-1.amaaaaaanmvrbeaac33bh4sxz3axwlayh3tdkavtj5bv7swe6fwrkgegwcia",
  "identity_context": {},
  "lifecycle_state": "Active",
  "resource_type": "LogAnalyticsEntity",
  "search_context": null,
  "system_tags": {},
  "time_created": "2023-07-07T12:55:23.909000+00:00"
}, {
  "additional_details": {},
  "availability_domain": null,
  "compartment_id": "ocid1.compartment.oc1..aaaaaaaapg6e3ceqxkmh27oeupg735l6k5nc2fcmq67l7pz3llebyhpkvlva",
  "defined_tags": {
    "Oracle-Tags": {
      "CreatedBy": "oscemea001/eric.vinck@oracle.com",
      "CreatedOn": "2021-07-07T08:37:46.304Z"
    },
    "osc": {
      "automatic_shutdown": "17:00_UTC",
      "automatic_startup": "07:00_UTC",
      "type": "user"
    }
  },
  "display_name": "generateConv",
  "freeform_tags": {},
  "identifier": "ocid1.dataflowapplication.oc1.eu-frankfurt-1.antheljsnmvrbeaak6mtz3fnwkk4dpjeinrq6lgrwl4t2orrdlwpevc4sdca",
  "identity_context": {},
  "lifecycle_state": "Active",
  "resource_type": "DataFlowApplication",
  "search_context": null,
  "system_tags": {},
  "time_created": "2021-07-07T08:37:47.876000+00:00"
}, {
  "additional_details": {},
  "availability_domain": null,
  "compartment_id": "ocid1.compartment.oc1..aaaaaaaapg6e3ceqxkmh27oeupg735l6k5nc2fcmq67l7pz3llebyhpkvlva",
  "defined_tags": {},
  "display_name": "generateConv",
  "freeform_tags": {},
  "identifier": "ocid1.dataflowrun.oc1.eu-frankfurt-1.antheljrnmvrbeaa2wadnhjoxf6wmvudmilibjwgdqwlflcnyvo75jraxtya",
  "identity_context": {},
  "lifecycle_state": "CANCELED",
  "resource_type": "DataFlowRun",
  "search_context": null,
  "system_tags": {},
  "time_created": "2021-07-07T13:09:45.466000+00:00"
}, {
  "additional_details": {},
  "availability_domain": null,
  "compartment_id": "ocid1.compartment.oc1..aaaaaaaapg6e3ceqxkmh27oeupg735l6k5nc2fcmq67l7pz3llebyhpkvlva",
  "defined_tags": {},
  "display_name": "generateConv",
  "freeform_tags": {},
  "identifier": "ocid1.dataflowrun.oc1.eu-frankfurt-1.antheljrnmvrbeaa75y6h5navu7pw5osc2zy5y3ig4kiazduieqfbrailsfa",
  "identity_context": {},
  "lifecycle_state": "SUCCEEDED",
  "resource_type": "DataFlowRun",
  "search_context": null,
  "system_tags": {},
  "time_created": "2021-07-08T16:09:13.822000+00:00"
}, {
  "additional_details": {},
  "availability_domain": null,
  "compartment_id": "ocid1.compartment.oc1..aaaaaaaapg6e3ceqxkmh27oeupg735l6k5nc2fcmq67l7pz3llebyhpkvlva",
  "defined_tags": {},
  "display_name": "generateConv",
  "freeform_tags": {},
  "identifier": "ocid1.dataflowrun.oc1.eu-frankfurt-1.antheljsnmvrbeaaa2bssspoj6dca75xzt3z7hatg2sbvqr2ww6zzgsztmga",
  "identity_context": {},
  "lifecycle_state": "SUCCEEDED",
  "resource_type": "DataFlowRun",
  "search_context": null,
  "system_tags": {},
  "time_created": "2021-07-10T19:09:19.155000+00:00"
}, {
  "additional_details": {},
  "availability_domain": null,
  "compartment_id": "ocid1.compartment.oc1..aaaaaaaapg6e3ceqxkmh27oeupg735l6k5nc2fcmq67l7pz3llebyhpkvlva",
  "defined_tags": {},
  "display_name": "generateConv",
  "freeform_tags": {},
  "identifier": "ocid1.dataflowrun.oc1.eu-frankfurt-1.antheljsnmvrbeaafm6slxwobgylkefcloounvcjdkhhfrpp75d6dqwmqdca",
  "identity_context": {},
  "lifecycle_state": "SUCCEEDED",
  "resource_type": "DataFlowRun",
  "search_context": null,
  "system_tags": {},
  "time_created": "2021-07-07T14:27:18.333000+00:00"
}, {
  "additional_details": {},
  "availability_domain": null,
  "compartment_id": "ocid1.compartment.oc1..aaaaaaaapg6e3ceqxkmh27oeupg735l6k5nc2fcmq67l7pz3llebyhpkvlva",
  "defined_tags": {},
  "display_name": "generateConv",
  "freeform_tags": {},
  "identifier": "ocid1.dataflowrun.oc1.eu-frankfurt-1.antheljsnmvrbeaag5l7pcd3t6qz5iyrvdpgvou3ls3imkn4dhk4t2cnkk3a",
  "identity_context": {},
  "lifecycle_state": "SUCCEEDED",
  "resource_type": "DataFlowRun",
  "search_context": null,
  "system_tags": {},
  "time_created": "2021-07-08T15:11:17.706000+00:00"
}, {
  "additional_details": {},
  "availability_domain": null,
  "compartment_id": "ocid1.compartment.oc1..aaaaaaaapg6e3ceqxkmh27oeupg735l6k5nc2fcmq67l7pz3llebyhpkvlva",
  "defined_tags": {},
  "display_name": "generateConv",
  "freeform_tags": {},
  "identifier": "ocid1.dataflowrun.oc1.eu-frankfurt-1.antheljsnmvrbeaamad7jblfqoviq7mvoztbo6lrjsprlwk6h7krb6z5fylq",
  "identity_context": {},
  "lifecycle_state": "SUCCEEDED",
  "resource_type": "DataFlowRun",
  "search_context": null,
  "system_tags": {},
  "time_created": "2021-07-07T14:05:45.920000+00:00"
}, {
  "additional_details": {},
  "availability_domain": null,
  "compartment_id": "ocid1.compartment.oc1..aaaaaaaapg6e3ceqxkmh27oeupg735l6k5nc2fcmq67l7pz3llebyhpkvlva",
  "defined_tags": {},
  "display_name": "generateConv",
  "freeform_tags": {},
  "identifier": "ocid1.dataflowrun.oc1.eu-frankfurt-1.antheljsnmvrbeaamvsc3gmpcsx6honexupw5nrudqbme3trushzas7yfo6a",
  "identity_context": {},
  "lifecycle_state": "SUCCEEDED",
  "resource_type": "DataFlowRun",
  "search_context": null,
  "system_tags": {},
  "time_created": "2021-07-08T10:02:37.794000+00:00"
}, {
  "additional_details": {},
  "availability_domain": null,
  "compartment_id": "ocid1.compartment.oc1..aaaaaaaapg6e3ceqxkmh27oeupg735l6k5nc2fcmq67l7pz3llebyhpkvlva",
  "defined_tags": {},
  "display_name": "generateConv",
  "freeform_tags": {},
  "identifier": "ocid1.dataflowrun.oc1.eu-frankfurt-1.antheljsnmvrbeaan6x4i3jlxmff6ahtjrid5ohtxop4ayzqacy7fhxic34a",
  "identity_context": {},
  "lifecycle_state": "CANCELED",
  "resource_type": "DataFlowRun",
  "search_context": null,
  "system_tags": {},
  "time_created": "2021-07-07T10:23:21.549000+00:00"
}, {
  "additional_details": {},
  "availability_domain": null,
  "compartment_id": "ocid1.compartment.oc1..aaaaaaaapg6e3ceqxkmh27oeupg735l6k5nc2fcmq67l7pz3llebyhpkvlva",
  "defined_tags": {},
  "display_name": "generateConv",
  "freeform_tags": {},
  "identifier": "ocid1.dataflowrun.oc1.eu-frankfurt-1.antheljtnmvrbeaam7l2juzwtui4bnsnclzmkl6idtlogvwjhh7zpzizqqra",
  "identity_context": {},
  "lifecycle_state": "CANCELED",
  "resource_type": "DataFlowRun",
  "search_context": null,
  "system_tags": {},
  "time_created": "2021-07-07T10:40:09.949000+00:00"
}, {
  "additional_details": {},
  "availability_domain": null,
  "compartment_id": "ocid1.compartment.oc1..aaaaaaaapg6e3ceqxkmh27oeupg735l6k5nc2fcmq67l7pz3llebyhpkvlva",
  "defined_tags": {},
  "display_name": "generateConv",
  "freeform_tags": {},
  "identifier": "ocid1.dataflowrun.oc1.eu-frankfurt-1.antheljtnmvrbeaaqif7zsetuilo5nr4gh37lu2qplmzieweu4gxqjwbmhxa",
  "identity_context": {},
  "lifecycle_state": "SUCCEEDED",
  "resource_type": "DataFlowRun",
  "search_context": null,
  "system_tags": {},
  "time_created": "2021-07-08T12:50:48.783000+00:00"
}, {
  "additional_details": {},
  "availability_domain": null,
  "compartment_id": "ocid1.compartment.oc1..aaaaaaaapg6e3ceqxkmh27oeupg735l6k5nc2fcmq67l7pz3llebyhpkvlva",
  "defined_tags": {},
  "display_name": "generateConv",
  "freeform_tags": {},
  "identifier": "ocid1.dataflowrun.oc1.eu-frankfurt-1.antheljtnmvrbeaas2hf4yoc6n3qx3zfrnt43l3r7m2h7xs5hoxd6kadh6wa",
  "identity_context": {},
  "lifecycle_state": "SUCCEEDED",
  "resource_type": "DataFlowRun",
  "search_context": null,
  "system_tags": {},
  "time_created": "2021-07-07T13:51:03.437000+00:00"
}, {
  "additional_details": {},
  "availability_domain": null,
  "compartment_id": "ocid1.compartment.oc1..aaaaaaaapg6e3ceqxkmh27oeupg735l6k5nc2fcmq67l7pz3llebyhpkvlva",
  "defined_tags": {},
  "display_name": "generateConv-3120M",
  "freeform_tags": {},
  "identifier": "ocid1.dataflowrun.oc1.eu-frankfurt-1.antheljsnmvrbeaadt7gxmyycoscnynq7fxztehnliomcsv2gswhwxqhev3q",
  "identity_context": {},
  "lifecycle_state": "FAILED",
  "resource_type": "DataFlowRun",
  "search_context": null,
  "system_tags": {},
  "time_created": "2021-07-09T07:47:25.041000+00:00"
}, {
  "additional_details": {},
  "availability_domain": null,
  "compartment_id": "ocid1.compartment.oc1..aaaaaaaapg6e3ceqxkmh27oeupg735l6k5nc2fcmq67l7pz3llebyhpkvlva",
  "defined_tags": {},
  "display_name": "metastore",
  "freeform_tags": {},
  "identifier": "ocid1.loganalyticsentity.oc1.eu-frankfurt-1.amaaaaaanmvrbeaas6ffaipod2rgqztek3xnemoehxxrtyen2yqpv7ryodzq",
  "identity_context": {},
  "lifecycle_state": "Active",
  "resource_type": "LogAnalyticsEntity",
  "search_context": null,
  "system_tags": {},
  "time_created": "2021-12-17T09:43:53.902000+00:00"
}, {
  "additional_details": {},
  "availability_domain": null,
  "compartment_id": "ocid1.compartment.oc1..aaaaaaaapg6e3ceqxkmh27oeupg735l6k5nc2fcmq67l7pz3llebyhpkvlva",
  "defined_tags": {
    "Oracle-Tags": {
      "CreatedBy": "oscemea001/eric.vinck@oracle.com",
      "CreatedOn": "2021-07-07T14:09:39.274Z"
    },
    "osc": {
      "automatic_shutdown": "17:00_UTC",
      "automatic_startup": "07:00_UTC",
      "type": "user"
    }
  },
  "display_name": "run.py",
  "freeform_tags": {},
  "identifier": "ocid1.dataflowapplication.oc1.eu-frankfurt-1.antheljsnmvrbeaagcr6nndjb367lttv64tiqxvbkrucyp5a7ewb63abjvya",
  "identity_context": {},
  "lifecycle_state": "Active",
  "resource_type": "DataFlowApplication",
  "search_context": null,
  "system_tags": {},
  "time_created": "2021-07-07T14:09:40.924000+00:00"
}, {
  "additional_details": {},
  "availability_domain": null,
  "compartment_id": "ocid1.compartment.oc1..aaaaaaaapg6e3ceqxkmh27oeupg735l6k5nc2fcmq67l7pz3llebyhpkvlva",
  "defined_tags": {},
  "display_name": "run.py",
  "freeform_tags": {},
  "identifier": "ocid1.dataflowrun.oc1.eu-frankfurt-1.antheljrnmvrbeaa4nluxljkphle3mbqqx3pmqz2igcpzurwp6nfak2olrmq",
  "identity_context": {},
  "lifecycle_state": "FAILED",
  "resource_type": "DataFlowRun",
  "search_context": null,
  "system_tags": {},
  "time_created": "2021-07-10T15:18:39.464000+00:00"
}, {
  "additional_details": {},
  "availability_domain": null,
  "compartment_id": "ocid1.compartment.oc1..aaaaaaaapg6e3ceqxkmh27oeupg735l6k5nc2fcmq67l7pz3llebyhpkvlva",
  "defined_tags": {},
  "display_name": "run.py",
  "freeform_tags": {},
  "identifier": "ocid1.dataflowrun.oc1.eu-frankfurt-1.antheljsnmvrbeaahjkwxxluhidcuqp2mxayevc75gye5auet4izfnppyrha",
  "identity_context": {},
  "lifecycle_state": "SUCCEEDED",
  "resource_type": "DataFlowRun",
  "search_context": null,
  "system_tags": {},
  "time_created": "2021-07-07T14:35:54.197000+00:00"
}, {
  "additional_details": {},
  "availability_domain": null,
  "compartment_id": "ocid1.compartment.oc1..aaaaaaaapg6e3ceqxkmh27oeupg735l6k5nc2fcmq67l7pz3llebyhpkvlva",
  "defined_tags": {},
  "display_name": "run.py",
  "freeform_tags": {},
  "identifier": "ocid1.dataflowrun.oc1.eu-frankfurt-1.antheljsnmvrbeaaxc5k7fpzfdqxn4gnki37cbqbhj7swugq4hvvdfw2pivq",
  "identity_context": {},
  "lifecycle_state": "SUCCEEDED",
  "resource_type": "DataFlowRun",
  "search_context": null,
  "system_tags": {},
  "time_created": "2021-07-08T13:06:32.467000+00:00"
}, {
  "additional_details": {},
  "availability_domain": null,
  "compartment_id": "ocid1.compartment.oc1..aaaaaaaapg6e3ceqxkmh27oeupg735l6k5nc2fcmq67l7pz3llebyhpkvlva",
  "defined_tags": {},
  "display_name": "run.py",
  "freeform_tags": {},
  "identifier": "ocid1.dataflowrun.oc1.eu-frankfurt-1.antheljsnmvrbeaaygf6io7tck55eesuu6wye7muf2ueuctiwrqixuc7fwnq",
  "identity_context": {},
  "lifecycle_state": "FAILED",
  "resource_type": "DataFlowRun",
  "search_context": null,
  "system_tags": {},
  "time_created": "2021-07-08T09:28:34.807000+00:00"
}, {
  "additional_details": {},
  "availability_domain": null,
  "compartment_id": "ocid1.compartment.oc1..aaaaaaaapg6e3ceqxkmh27oeupg735l6k5nc2fcmq67l7pz3llebyhpkvlva",
  "defined_tags": {},
  "display_name": "run.py",
  "freeform_tags": {},
  "identifier": "ocid1.dataflowrun.oc1.eu-frankfurt-1.antheljtnmvrbeaa4hs4uq6rjoveezqsc37tjei2nk4xspmzbj2jyq3esl7a",
  "identity_context": {},
  "lifecycle_state": "SUCCEEDED",
  "resource_type": "DataFlowRun",
  "search_context": null,
  "system_tags": {},
  "time_created": "2021-07-07T14:42:18.317000+00:00"
}, {
  "additional_details": {},
  "availability_domain": null,
  "compartment_id": "ocid1.compartment.oc1..aaaaaaaapg6e3ceqxkmh27oeupg735l6k5nc2fcmq67l7pz3llebyhpkvlva",
  "defined_tags": {},
  "display_name": "run.py",
  "freeform_tags": {},
  "identifier": "ocid1.dataflowrun.oc1.eu-frankfurt-1.antheljtnmvrbeaaeaoxmomrcy3tqxmm2z6zrpjcv6iwmajs5qxi7y6et7mq",
  "identity_context": {},
  "lifecycle_state": "SUCCEEDED",
  "resource_type": "DataFlowRun",
  "search_context": null,
  "system_tags": {},
  "time_created": "2021-07-07T14:15:48.579000+00:00"
}, {
  "additional_details": {},
  "availability_domain": null,
  "compartment_id": "ocid1.compartment.oc1..aaaaaaaapg6e3ceqxkmh27oeupg735l6k5nc2fcmq67l7pz3llebyhpkvlva",
  "defined_tags": {},
  "display_name": "run.py",
  "freeform_tags": {},
  "identifier": "ocid1.dataflowrun.oc1.eu-frankfurt-1.antheljtnmvrbeaafw7teh4g2vkqk7c3vxumtcuixaqul4tq5jvesfl74qsa",
  "identity_context": {},
  "lifecycle_state": "FAILED",
  "resource_type": "DataFlowRun",
  "search_context": null,
  "system_tags": {},
  "time_created": "2021-07-08T09:50:43.121000+00:00"
}, {
  "additional_details": {},
  "availability_domain": null,
  "compartment_id": "ocid1.compartment.oc1..aaaaaaaapg6e3ceqxkmh27oeupg735l6k5nc2fcmq67l7pz3llebyhpkvlva",
  "defined_tags": {},
  "display_name": "run.py",
  "freeform_tags": {},
  "identifier": "ocid1.dataflowrun.oc1.eu-frankfurt-1.antheljtnmvrbeaahw74udf3g3ds3zks4sceidhkocs5y4wwchl3frhc34fa",
  "identity_context": {},
  "lifecycle_state": "SUCCEEDED",
  "resource_type": "DataFlowRun",
  "search_context": null,
  "system_tags": {},
  "time_created": "2021-07-08T11:15:59.600000+00:00"
}, {
  "additional_details": {},
  "availability_domain": null,
  "compartment_id": "ocid1.compartment.oc1..aaaaaaaapg6e3ceqxkmh27oeupg735l6k5nc2fcmq67l7pz3llebyhpkvlva",
  "defined_tags": {},
  "display_name": "run1",
  "freeform_tags": {},
  "identifier": "ocid1.dataflowrun.oc1.eu-frankfurt-1.antheljtnmvrbeaa4j6yrrp2qgnkulkkvbz6ebucfln6a3fl5iwxbzpe3dnq",
  "identity_context": {},
  "lifecycle_state": "FAILED",
  "resource_type": "DataFlowRun",
  "search_context": null,
  "system_tags": {},
  "time_created": "2021-07-07T08:44:16.584000+00:00"
}, {
  "additional_details": {},
  "availability_domain": null,
  "compartment_id": "ocid1.compartment.oc1..aaaaaaaapg6e3ceqxkmh27oeupg735l6k5nc2fcmq67l7pz3llebyhpkvlva",
  "defined_tags": {},
  "display_name": "run1",
  "freeform_tags": {},
  "identifier": "ocid1.dataflowrun.oc1.eu-frankfurt-1.antheljtnmvrbeaamtp7mgozi6u6cs3lahufvrb26fmp4un7p6q7tt535aia",
  "identity_context": {},
  "lifecycle_state": "CANCELED",
  "resource_type": "DataFlowRun",
  "search_context": null,
  "system_tags": {},
  "time_created": "2021-07-07T08:56:39.193000+00:00"
}, {
  "additional_details": {},
  "availability_domain": null,
  "compartment_id": "ocid1.compartment.oc1..aaaaaaaapg6e3ceqxkmh27oeupg735l6k5nc2fcmq67l7pz3llebyhpkvlva",
  "defined_tags": {
    "Oracle-Tags": {
      "CreatedBy": "oscemea001/eric.vinck@oracle.com",
      "CreatedOn": "2021-07-08T16:55:05.428Z"
    },
    "osc": {
      "automatic_shutdown": "17:00_UTC",
      "automatic_startup": "07:00_UTC",
      "type": "user"
    }
  },
  "display_name": "run1.py",
  "freeform_tags": {},
  "identifier": "ocid1.dataflowapplication.oc1.eu-frankfurt-1.antheljtnmvrbeaabhdct6xru46nfmzeertc7q37ryxgsyfjm564sdveen5q",
  "identity_context": {},
  "lifecycle_state": "Active",
  "resource_type": "DataFlowApplication",
  "search_context": null,
  "system_tags": {},
  "time_created": "2021-07-08T16:55:06.863000+00:00"
}, {
  "additional_details": {},
  "availability_domain": null,
  "compartment_id": "ocid1.compartment.oc1..aaaaaaaapg6e3ceqxkmh27oeupg735l6k5nc2fcmq67l7pz3llebyhpkvlva",
  "defined_tags": {},
  "display_name": "run1.py",
  "freeform_tags": {},
  "identifier": "ocid1.dataflowrun.oc1.eu-frankfurt-1.antheljrnmvrbeaa4xttlamahzd3xjeg7x3ckswq5zm26x4q7lzdp2x4wfzq",
  "identity_context": {},
  "lifecycle_state": "FAILED",
  "resource_type": "DataFlowRun",
  "search_context": null,
  "system_tags": {},
  "time_created": "2021-07-08T17:50:15.876000+00:00"
}, {
  "additional_details": {},
  "availability_domain": null,
  "compartment_id": "ocid1.compartment.oc1..aaaaaaaapg6e3ceqxkmh27oeupg735l6k5nc2fcmq67l7pz3llebyhpkvlva",
  "defined_tags": {},
  "display_name": "run1.py",
  "freeform_tags": {},
  "identifier": "ocid1.dataflowrun.oc1.eu-frankfurt-1.antheljrnmvrbeaa55fnew4vyert7xj67zf7wylewzoxvyrmqlxjwcnc7kea",
  "identity_context": {},
  "lifecycle_state": "FAILED",
  "resource_type": "DataFlowRun",
  "search_context": null,
  "system_tags": {},
  "time_created": "2021-07-09T23:51:15.378000+00:00"
}, {
  "additional_details": {},
  "availability_domain": null,
  "compartment_id": "ocid1.compartment.oc1..aaaaaaaapg6e3ceqxkmh27oeupg735l6k5nc2fcmq67l7pz3llebyhpkvlva",
  "defined_tags": {},
  "display_name": "run1.py",
  "freeform_tags": {},
  "identifier": "ocid1.dataflowrun.oc1.eu-frankfurt-1.antheljrnmvrbeaahwwedfedvljuy5psn2xvw2j7z6iys3fbih3lqh52avnq",
  "identity_context": {},
  "lifecycle_state": "SUCCEEDED",
  "resource_type": "DataFlowRun",
  "search_context": null,
  "system_tags": {},
  "time_created": "2021-07-12T20:46:26.843000+00:00"
}, {
  "additional_details": {},
  "availability_domain": null,
  "compartment_id": "ocid1.compartment.oc1..aaaaaaaapg6e3ceqxkmh27oeupg735l6k5nc2fcmq67l7pz3llebyhpkvlva",
  "defined_tags": {},
  "display_name": "run1.py",
  "freeform_tags": {},
  "identifier": "ocid1.dataflowrun.oc1.eu-frankfurt-1.antheljrnmvrbeaakaxeymmeygpxvrvsdfmqvfxib43aplrwijhhw2ni7f7a",
  "identity_context": {},
  "lifecycle_state": "SUCCEEDED",
  "resource_type": "DataFlowRun",
  "search_context": null,
  "system_tags": {},
  "time_created": "2021-07-10T19:24:52.538000+00:00"
}, {
  "additional_details": {},
  "availability_domain": null,
  "compartment_id": "ocid1.compartment.oc1..aaaaaaaapg6e3ceqxkmh27oeupg735l6k5nc2fcmq67l7pz3llebyhpkvlva",
  "defined_tags": {},
  "display_name": "run1.py",
  "freeform_tags": {},
  "identifier": "ocid1.dataflowrun.oc1.eu-frankfurt-1.antheljrnmvrbeaaubwuq2t5ekgomt55qcojwrgkbtny2tkyoxqronflar3a",
  "identity_context": {},
  "lifecycle_state": "SUCCEEDED",
  "resource_type": "DataFlowRun",
  "search_context": null,
  "system_tags": {},
  "time_created": "2021-07-10T21:38:37.262000+00:00"
}, {
  "additional_details": {},
  "availability_domain": null,
  "compartment_id": "ocid1.compartment.oc1..aaaaaaaapg6e3ceqxkmh27oeupg735l6k5nc2fcmq67l7pz3llebyhpkvlva",
  "defined_tags": {},
  "display_name": "run1.py",
  "freeform_tags": {},
  "identifier": "ocid1.dataflowrun.oc1.eu-frankfurt-1.antheljsnmvrbeaa5gesc6zl6wdq7456ans5ceaqgzgmgo3xgxmbllob2t2a",
  "identity_context": {},
  "lifecycle_state": "SUCCEEDED",
  "resource_type": "DataFlowRun",
  "search_context": null,
  "system_tags": {},
  "time_created": "2021-07-12T21:26:49.059000+00:00"
}, {
  "additional_details": {},
  "availability_domain": null,
  "compartment_id": "ocid1.compartment.oc1..aaaaaaaapg6e3ceqxkmh27oeupg735l6k5nc2fcmq67l7pz3llebyhpkvlva",
  "defined_tags": {},
  "display_name": "run1.py",
  "freeform_tags": {},
  "identifier": "ocid1.dataflowrun.oc1.eu-frankfurt-1.antheljsnmvrbeaa7zv66maa44spbtbkm53j3okqzoehgpvnkrl7557xaftq",
  "identity_context": {},
  "lifecycle_state": "SUCCEEDED",
  "resource_type": "DataFlowRun",
  "search_context": null,
  "system_tags": {},
  "time_created": "2021-07-12T16:59:36.273000+00:00"
}, {
  "additional_details": {},
  "availability_domain": null,
  "compartment_id": "ocid1.compartment.oc1..aaaaaaaapg6e3ceqxkmh27oeupg735l6k5nc2fcmq67l7pz3llebyhpkvlva",
  "defined_tags": {},
  "display_name": "run1.py",
  "freeform_tags": {},
  "identifier": "ocid1.dataflowrun.oc1.eu-frankfurt-1.antheljsnmvrbeaabc4eyrjeu6b2nvpn7jyebjbj4jboexygdi26dtqiiyma",
  "identity_context": {},
  "lifecycle_state": "SUCCEEDED",
  "resource_type": "DataFlowRun",
  "search_context": null,
  "system_tags": {},
  "time_created": "2021-07-12T21:02:35.316000+00:00"
}, {
  "additional_details": {},
  "availability_domain": null,
  "compartment_id": "ocid1.compartment.oc1..aaaaaaaapg6e3ceqxkmh27oeupg735l6k5nc2fcmq67l7pz3llebyhpkvlva",
  "defined_tags": {},
  "display_name": "run1.py",
  "freeform_tags": {},
  "identifier": "ocid1.dataflowrun.oc1.eu-frankfurt-1.antheljsnmvrbeaad7s4fojwwqxdmqcre57ehypex2srxgvljp3wiuowjcrq",
  "identity_context": {},
  "lifecycle_state": "FAILED",
  "resource_type": "DataFlowRun",
  "search_context": null,
  "system_tags": {},
  "time_created": "2021-07-08T18:28:29.626000+00:00"
}, {
  "additional_details": {},
  "availability_domain": null,
  "compartment_id": "ocid1.compartment.oc1..aaaaaaaapg6e3ceqxkmh27oeupg735l6k5nc2fcmq67l7pz3llebyhpkvlva",
  "defined_tags": {},
  "display_name": "run1.py",
  "freeform_tags": {},
  "identifier": "ocid1.dataflowrun.oc1.eu-frankfurt-1.antheljsnmvrbeaaoml4ngb25ibtkqf2wdmrhebnxqwo3xitlqb2lxonoamq",
  "identity_context": {},
  "lifecycle_state": "FAILED",
  "resource_type": "DataFlowRun",
  "search_context": null,
  "system_tags": {},
  "time_created": "2021-08-23T09:57:45.557000+00:00"
}, {
  "additional_details": {},
  "availability_domain": null,
  "compartment_id": "ocid1.compartment.oc1..aaaaaaaapg6e3ceqxkmh27oeupg735l6k5nc2fcmq67l7pz3llebyhpkvlva",
  "defined_tags": {},
  "display_name": "run1.py",
  "freeform_tags": {},
  "identifier": "ocid1.dataflowrun.oc1.eu-frankfurt-1.antheljsnmvrbeaav3h4qgxmcpttvxi3xegkjxltg4ylhymqpxl36ojdkfdq",
  "identity_context": {},
  "lifecycle_state": "SUCCEEDED",
  "resource_type": "DataFlowRun",
  "search_context": null,
  "system_tags": {},
  "time_created": "2021-07-12T16:40:49.154000+00:00"
}, {
  "additional_details": {},
  "availability_domain": null,
  "compartment_id": "ocid1.compartment.oc1..aaaaaaaapg6e3ceqxkmh27oeupg735l6k5nc2fcmq67l7pz3llebyhpkvlva",
  "defined_tags": {},
  "display_name": "run1.py",
  "freeform_tags": {},
  "identifier": "ocid1.dataflowrun.oc1.eu-frankfurt-1.antheljsnmvrbeaayww4hytoeqaxhjump4n27ygmzm453n73rdlef7sqgela",
  "identity_context": {},
  "lifecycle_state": "FAILED",
  "resource_type": "DataFlowRun",
  "search_context": null,
  "system_tags": {},
  "time_created": "2021-07-08T18:14:50.487000+00:00"
}, {
  "additional_details": {},
  "availability_domain": null,
  "compartment_id": "ocid1.compartment.oc1..aaaaaaaapg6e3ceqxkmh27oeupg735l6k5nc2fcmq67l7pz3llebyhpkvlva",
  "defined_tags": {},
  "display_name": "run1.py",
  "freeform_tags": {},
  "identifier": "ocid1.dataflowrun.oc1.eu-frankfurt-1.antheljtnmvrbeaa6c6so3ryavgc2qehc3lcmszp4fiilws4sgiyp6h7vpgq",
  "identity_context": {},
  "lifecycle_state": "SUCCEEDED",
  "resource_type": "DataFlowRun",
  "search_context": null,
  "system_tags": {},
  "time_created": "2021-07-12T16:28:09.201000+00:00"
}, {
  "additional_details": {},
  "availability_domain": null,
  "compartment_id": "ocid1.compartment.oc1..aaaaaaaapg6e3ceqxkmh27oeupg735l6k5nc2fcmq67l7pz3llebyhpkvlva",
  "defined_tags": {},
  "display_name": "run1.py",
  "freeform_tags": {},
  "identifier": "ocid1.dataflowrun.oc1.eu-frankfurt-1.antheljtnmvrbeaac3eekcfqqqtrr2kugsd7kwgd4hepqh7p2pkb7wl33cuq",
  "identity_context": {},
  "lifecycle_state": "FAILED",
  "resource_type": "DataFlowRun",
  "search_context": null,
  "system_tags": {},
  "time_created": "2021-07-08T18:36:23.120000+00:00"
}, {
  "additional_details": {},
  "availability_domain": null,
  "compartment_id": "ocid1.compartment.oc1..aaaaaaaapg6e3ceqxkmh27oeupg735l6k5nc2fcmq67l7pz3llebyhpkvlva",
  "defined_tags": {},
  "display_name": "run1.py",
  "freeform_tags": {},
  "identifier": "ocid1.dataflowrun.oc1.eu-frankfurt-1.antheljtnmvrbeaaelyi5brjdpctbtg6wo5oeijektyrcjoxmbnvs7i6onta",
  "identity_context": {},
  "lifecycle_state": "FAILED",
  "resource_type": "DataFlowRun",
  "search_context": null,
  "system_tags": {},
  "time_created": "2021-07-08T18:49:31.099000+00:00"
}, {
  "additional_details": {},
  "availability_domain": null,
  "compartment_id": "ocid1.compartment.oc1..aaaaaaaapg6e3ceqxkmh27oeupg735l6k5nc2fcmq67l7pz3llebyhpkvlva",
  "defined_tags": {},
  "display_name": "run1.py",
  "freeform_tags": {},
  "identifier": "ocid1.dataflowrun.oc1.eu-frankfurt-1.antheljtnmvrbeaaidndo73e6qt4qkq5ipakonhsu4rojaeowhgtpdtlzjqa",
  "identity_context": {},
  "lifecycle_state": "SUCCEEDED",
  "resource_type": "DataFlowRun",
  "search_context": null,
  "system_tags": {},
  "time_created": "2021-07-12T17:51:56.311000+00:00"
}, {
  "additional_details": {},
  "availability_domain": null,
  "compartment_id": "ocid1.compartment.oc1..aaaaaaaapg6e3ceqxkmh27oeupg735l6k5nc2fcmq67l7pz3llebyhpkvlva",
  "defined_tags": {},
  "display_name": "run1.py",
  "freeform_tags": {},
  "identifier": "ocid1.dataflowrun.oc1.eu-frankfurt-1.antheljtnmvrbeaantkjbypkriq22godh7thu4vrtbcrqaenha7x3txco5vq",
  "identity_context": {},
  "lifecycle_state": "FAILED",
  "resource_type": "DataFlowRun",
  "search_context": null,
  "system_tags": {},
  "time_created": "2021-07-08T16:55:58.350000+00:00"
}, {
  "additional_details": {},
  "availability_domain": null,
  "compartment_id": "ocid1.compartment.oc1..aaaaaaaapg6e3ceqxkmh27oeupg735l6k5nc2fcmq67l7pz3llebyhpkvlva",
  "defined_tags": {},
  "display_name": "run1.py",
  "freeform_tags": {},
  "identifier": "ocid1.dataflowrun.oc1.eu-frankfurt-1.antheljtnmvrbeaarzgcqqn2fivpryn452bposoknycqf7t4wmoxqicqguwa",
  "identity_context": {},
  "lifecycle_state": "SUCCEEDED",
  "resource_type": "DataFlowRun",
  "search_context": null,
  "system_tags": {},
  "time_created": "2021-09-10T15:56:06.097000+00:00"
}, {
  "additional_details": {},
  "availability_domain": null,
  "compartment_id": "ocid1.compartment.oc1..aaaaaaaapg6e3ceqxkmh27oeupg735l6k5nc2fcmq67l7pz3llebyhpkvlva",
  "defined_tags": {},
  "display_name": "run1.py",
  "freeform_tags": {},
  "identifier": "ocid1.dataflowrun.oc1.eu-frankfurt-1.antheljtnmvrbeaaumd2vmj4it7whdovkjwsunhpgayh6jnf4sa3mhq5vi4q",
  "identity_context": {},
  "lifecycle_state": "SUCCEEDED",
  "resource_type": "DataFlowRun",
  "search_context": null,
  "system_tags": {},
  "time_created": "2021-07-12T16:49:39.673000+00:00"
}, {
  "additional_details": {},
  "availability_domain": null,
  "compartment_id": "ocid1.compartment.oc1..aaaaaaaapg6e3ceqxkmh27oeupg735l6k5nc2fcmq67l7pz3llebyhpkvlva",
  "defined_tags": {},
  "display_name": "run1.py",
  "freeform_tags": {},
  "identifier": "ocid1.dataflowrun.oc1.eu-frankfurt-1.antheljtnmvrbeaayhaiaobs3hjbq3esmn2g53hlzpi3cnr7vk7lbs6iqmea",
  "identity_context": {},
  "lifecycle_state": "FAILED",
  "resource_type": "DataFlowRun",
  "search_context": null,
  "system_tags": {},
  "time_created": "2021-07-10T00:10:40.781000+00:00"
}, {
  "additional_details": {},
  "availability_domain": null,
  "compartment_id": "ocid1.compartment.oc1..aaaaaaaapg6e3ceqxkmh27oeupg735l6k5nc2fcmq67l7pz3llebyhpkvlva",
  "defined_tags": {
    "Oracle-Tags": {
      "CreatedBy": "oscemea001/eric.vinck@oracle.com",
      "CreatedOn": "2021-07-12T16:25:34.273Z"
    },
    "osc": {
      "automatic_shutdown": "17:00_UTC",
      "automatic_startup": "07:00_UTC",
      "type": "user"
    }
  },
  "display_name": "subnet-20210712-1820",
  "freeform_tags": {},
  "identifier": "ocid1.subnet.oc1.eu-frankfurt-1.aaaaaaaazu4tesextpv5vuzfbss4katcnsruqo2tbrd2t36l4oolz3j32xdq",
  "identity_context": {},
  "lifecycle_state": "AVAILABLE",
  "resource_type": "Subnet",
  "search_context": null,
  "system_tags": {},
  "time_created": "2021-07-12T16:25:34.320000+00:00"
}, {
  "additional_details": {},
  "availability_domain": null,
  "compartment_id": "ocid1.compartment.oc1..aaaaaaaapg6e3ceqxkmh27oeupg735l6k5nc2fcmq67l7pz3llebyhpkvlva",
  "defined_tags": {
    "Oracle-Tags": {
      "CreatedBy": "oscemea001/eric.vinck@oracle.com",
      "CreatedOn": "2021-07-12T16:25:34.273Z"
    },
    "osc": {
      "automatic_shutdown": "17:00_UTC",
      "automatic_startup": "07:00_UTC",
      "type": "user"
    }
  },
  "display_name": "subnet07121825.vcn07121825.oraclevcn.com",
  "freeform_tags": {},
  "identifier": "ocid1.dns-zone.oc1.eu-frankfurt-1.aaaaaaaacqnzlb3r3srwewn2d6xx2g3bvnakycperkavhb5rtgvy3vkab5xa",
  "identity_context": {},
  "lifecycle_state": "ACTIVE",
  "resource_type": "CustomerDnsZone",
  "search_context": null,
  "system_tags": {},
  "time_created": "2021-07-12T16:25:35.101000+00:00"
}, {
  "additional_details": {},
  "availability_domain": "",
  "compartment_id": "ocid1.compartment.oc1..aaaaaaaapg6e3ceqxkmh27oeupg735l6k5nc2fcmq67l7pz3llebyhpkvlva",
  "defined_tags": {
    "Oracle-Tags": {
      "CreatedBy": "oscemea001/eric.vinck@oracle.com",
      "CreatedOn": "2021-07-15T22:24:05.543Z"
    },
    "osc": {
      "automatic_shutdown": "17:00_UTC",
      "automatic_startup": "07:00_UTC",
      "type": "user"
    }
  },
  "display_name": "tutorial",
  "freeform_tags": {},
  "identifier": "ocid1.bucket.oc1.eu-frankfurt-1.aaaaaaaafkennc5ptyzgfzcqs6ckkxgg4pqhopd5mf2ckuvenqzwsdt5hzwq",
  "identity_context": {},
  "lifecycle_state": "active",
  "resource_type": "Bucket",
  "search_context": null,
  "system_tags": {},
  "time_created": "2021-07-15T22:24:05.550000+00:00"
}, {
  "additional_details": {},
  "availability_domain": null,
  "compartment_id": "ocid1.compartment.oc1..aaaaaaaapg6e3ceqxkmh27oeupg735l6k5nc2fcmq67l7pz3llebyhpkvlva",
  "defined_tags": {},
  "display_name": "tutorial",
  "freeform_tags": {},
  "identifier": "ocid1.loganalyticsentity.oc1.eu-frankfurt-1.amaaaaaanmvrbeaao4kjid4gec66waxbbtrnoxb3hhyddg5l32k4z37zyb7a",
  "identity_context": {},
  "lifecycle_state": "Active",
  "resource_type": "LogAnalyticsEntity",
  "search_context": null,
  "system_tags": {},
  "time_created": "2021-12-17T09:43:53.902000+00:00"
}, {
  "additional_details": {},
  "availability_domain": null,
  "compartment_id": "ocid1.compartment.oc1..aaaaaaaapg6e3ceqxkmh27oeupg735l6k5nc2fcmq67l7pz3llebyhpkvlva",
  "defined_tags": {
    "Oracle-Tags": {
      "CreatedBy": "oscemea001/eric.vinck@oracle.com",
      "CreatedOn": "2021-07-12T16:25:32.061Z"
    },
    "osc": {
      "automatic_shutdown": "17:00_UTC",
      "automatic_startup": "07:00_UTC",
      "type": "user"
    }
  },
  "display_name": "vcn-20210712-1820",
  "freeform_tags": {},
  "identifier": "ocid1.dnsresolver.oc1.eu-frankfurt-1.amaaaaaanmvrbeaaooczogcgbuomq576g3emqxjkbqljbcbimlix63oop6vq",
  "identity_context": {},
  "lifecycle_state": "ACTIVE",
  "resource_type": "DnsResolver",
  "search_context": null,
  "system_tags": {},
  "time_created": "2021-07-12T16:25:32.894000+00:00"
}, {
  "additional_details": {},
  "availability_domain": null,
  "compartment_id": "ocid1.compartment.oc1..aaaaaaaapg6e3ceqxkmh27oeupg735l6k5nc2fcmq67l7pz3llebyhpkvlva",
  "defined_tags": {
    "Oracle-Tags": {
      "CreatedBy": "oscemea001/eric.vinck@oracle.com",
      "CreatedOn": "2021-07-12T16:25:32.061Z"
    },
    "osc": {
      "automatic_shutdown": "17:00_UTC",
      "automatic_startup": "07:00_UTC",
      "type": "user"
    }
  },
  "display_name": "vcn-20210712-1820",
  "freeform_tags": {},
  "identifier": "ocid1.dnsview.oc1.eu-frankfurt-1.aaaaaaaa3aii3ykl5pstxmyisv7hl5pwupjbgsbz7srdg3z7bybbtlsiwl2a",
  "identity_context": {},
  "lifecycle_state": "ACTIVE",
  "resource_type": "DnsView",
  "search_context": null,
  "system_tags": {},
  "time_created": "2021-07-12T16:25:32.894000+00:00"
}, {
  "additional_details": {},
  "availability_domain": null,
  "compartment_id": "ocid1.compartment.oc1..aaaaaaaapg6e3ceqxkmh27oeupg735l6k5nc2fcmq67l7pz3llebyhpkvlva",
  "defined_tags": {
    "Oracle-Tags": {
      "CreatedBy": "oscemea001/eric.vinck@oracle.com",
      "CreatedOn": "2021-07-12T16:25:32.061Z"
    },
    "osc": {
      "automatic_shutdown": "17:00_UTC",
      "automatic_startup": "07:00_UTC",
      "type": "user"
    }
  },
  "display_name": "vcn-20210712-1820",
  "freeform_tags": {},
  "identifier": "ocid1.vcn.oc1.eu-frankfurt-1.amaaaaaanmvrbeaahz7zmklo2wlmvvafjqinlulgwor2t4astel6yyloj5mq",
  "identity_context": {},
  "lifecycle_state": "AVAILABLE",
  "resource_type": "Vcn",
  "search_context": null,
  "system_tags": {},
  "time_created": "2021-07-12T16:25:32.187000+00:00"
}, {
  "additional_details": {},
  "availability_domain": null,
  "compartment_id": "ocid1.compartment.oc1..aaaaaaaapg6e3ceqxkmh27oeupg735l6k5nc2fcmq67l7pz3llebyhpkvlva",
  "defined_tags": {},
  "display_name": "SA_1654913528832",
  "freeform_tags": {},
  "identifier": "ocid1.datasafesecurityassessment.oc1.iad.abuwcljsbiuldvkodilu5ztgdqgfwraj4anv2vg6bmiypzmzu5xdnasv4krq",
  "identity_context": {},
  "lifecycle_state": "SUCCEEDED",
  "resource_type": "DataSafeSecurityAssessment",
  "search_context": null,
  "system_tags": {},
  "time_created": "2022-06-11T02:12:08.839000+00:00"
}, {
  "additional_details": {},
  "availability_domain": null,
  "compartment_id": "ocid1.compartment.oc1..aaaaaaaapg6e3ceqxkmh27oeupg735l6k5nc2fcmq67l7pz3llebyhpkvlva",
  "defined_tags": {},
  "display_name": "UA_1654907580351",
  "freeform_tags": {},
  "identifier": "ocid1.datasafeuserassessment.oc1.iad.abuwcljrs2ojjcp55txzgfoyrd7fyivbfstdh5lgymqacomuefdnkglsuhsa",
  "identity_context": {},
  "lifecycle_state": "SUCCEEDED",
  "resource_type": "DataSafeUserAssessment",
  "search_context": null,
  "system_tags": {},
  "time_created": "2022-06-11T00:33:00.361000+00:00"
}, {
  "additional_details": {},
  "availability_domain": null,
  "compartment_id": "ocid1.compartment.oc1..aaaaaaaapg6e3ceqxkmh27oeupg735l6k5nc2fcmq67l7pz3llebyhpkvlva",
  "defined_tags": {},
  "display_name": "UA_1658563369266",
  "freeform_tags": {},
  "identifier": "ocid1.datasafeuserassessment.oc1.uk-london-1.abwgiljt7c3gionqgj423n462qd55rcvl5hvuhnz5lvf3jehf2f2ho2gpjxa",
  "identity_context": {},
  "lifecycle_state": "SUCCEEDED",
  "resource_type": "DataSafeUserAssessment",
  "search_context": null,
  "system_tags": {},
  "time_created": "2022-07-23T08:02:49.274000+00:00"
}]