[{
  "additional_details": {},
  "availability_domain": null,
  "compartment_id": "ocid1.compartment.oc1..aaaaaaaao4an2ija2us4absknlvmf5g7u2tmkh654kurkh4uj2rjnfhb5jua",
  "defined_tags": {},
  "display_name": "SA_1654855008019",
  "freeform_tags": {},
  "identifier": "ocid1.datasafesecurityassessment.oc1.eu-frankfurt-1.abtheljtfstl4se3nri4tsckbiuifjxjv2dv5yyqwq3v2phiugwkgtatggwa",
  "identity_context": {},
  "lifecycle_state": "SUCCEEDED",
  "resource_type": "DataSafeSecurityAssessment",
  "search_context": null,
  "system_tags": {},
  "time_created": "2022-06-10T09:56:48.023000+00:00"
}, {
  "additional_details": {},
  "availability_domain": null,
  "compartment_id": "ocid1.compartment.oc1..aaaaaaaao4an2ija2us4absknlvmf5g7u2tmkh654kurkh4uj2rjnfhb5jua",
  "defined_tags": {},
  "display_name": "UA_1654856320607",
  "freeform_tags": {},
  "identifier": "ocid1.datasafeuserassessment.oc1.eu-frankfurt-1.abtheljtadlmzyohqyoifth3fshlwfqpgaau4op56nd35kzutblnxvw45hfa",
  "identity_context": {},
  "lifecycle_state": "SUCCEEDED",
  "resource_type": "DataSafeUserAssessment",
  "search_context": null,
  "system_tags": {},
  "time_created": "2022-06-10T10:18:40.612000+00:00"
}, {
  "additional_details": {},
  "availability_domain": null,
  "compartment_id": "ocid1.compartment.oc1..aaaaaaaao4an2ija2us4absknlvmf5g7u2tmkh654kurkh4uj2rjnfhb5jua",
  "defined_tags": {},
  "display_name": "SA_1654913509014",
  "freeform_tags": {},
  "identifier": "ocid1.datasafesecurityassessment.oc1.iad.abuwcljs6acthqfgysjmto75wlolph26ag2v6vcotwfneigemefrl4lrhnuq",
  "identity_context": {},
  "lifecycle_state": "SUCCEEDED",
  "resource_type": "DataSafeSecurityAssessment",
  "search_context": null,
  "system_tags": {},
  "time_created": "2022-06-11T02:11:49.019000+00:00"
}, {
  "additional_details": {},
  "availability_domain": null,
  "compartment_id": "ocid1.compartment.oc1..aaaaaaaao4an2ija2us4absknlvmf5g7u2tmkh654kurkh4uj2rjnfhb5jua",
  "defined_tags": {},
  "display_name": "UA_1654907583244",
  "freeform_tags": {},
  "identifier": "ocid1.datasafeuserassessment.oc1.iad.abuwcljtrnkfj2fgf7tlkvjrocrwzmo6pgvj64jvfedonrsrfyd7ri4hkicq",
  "identity_context": {},
  "lifecycle_state": "SUCCEEDED",
  "resource_type": "DataSafeUserAssessment",
  "search_context": null,
  "system_tags": {},
  "time_created": "2022-06-11T00:33:03.249000+00:00"
}, {
  "additional_details": {},
  "availability_domain": null,
  "compartment_id": "ocid1.compartment.oc1..aaaaaaaao4an2ija2us4absknlvmf5g7u2tmkh654kurkh4uj2rjnfhb5jua",
  "defined_tags": {},
  "display_name": "UA_1658563285673",
  "freeform_tags": {},
  "identifier": "ocid1.datasafeuserassessment.oc1.uk-london-1.abwgiljtmexb2mpn3hcptjglgpoq6o4zqahhwyo6rop7pco6aimih4n7yxyq",
  "identity_context": {},
  "lifecycle_state": "SUCCEEDED",
  "resource_type": "DataSafeUserAssessment",
  "search_context": null,
  "system_tags": {},
  "time_created": "2022-07-23T08:01:25.677000+00:00"
}]