[{
  "additional_details": {},
  "availability_domain": null,
  "compartment_id": "ocid1.compartment.oc1..aaaaaaaa5hezxb625e2jesof6g4bt2wuzndxz6bf4pvkjzhecies4wvc44jq",
  "defined_tags": {
    "Oracle-Tags": {
      "CreatedBy": "oscemea001/rob.watson@oracle.com",
      "CreatedOn": "2021-08-11T12:11:27.921Z"
    },
    "osc": {
      "automatic_shutdown": "off",
      "automatic_startup": "off",
      "type": "user"
    }
  },
  "display_name": "ADWAP",
  "freeform_tags": {},
  "identifier": "ocid1.autonomousdatabase.oc1.eu-frankfurt-1.antheljtnmvrbeaa2myoyz2im27d3bprb6bqa4nuoz6liojkvhipqnmlat5a",
  "identity_context": {},
  "lifecycle_state": "STOPPED",
  "resource_type": "AutonomousDatabase",
  "search_context": null,
  "system_tags": {},
  "time_created": "2021-08-11T12:11:27.927000+00:00"
}, {
  "additional_details": {},
  "availability_domain": null,
  "compartment_id": "ocid1.compartment.oc1..aaaaaaaa5hezxb625e2jesof6g4bt2wuzndxz6bf4pvkjzhecies4wvc44jq",
  "defined_tags": {
    "Oracle-Tags": {
      "CreatedBy": "oscemea001/rob.watson@oracle.com",
      "CreatedOn": "2021-08-12T08:21:05.464Z"
    },
    "osc": {
      "automatic_shutdown": "off",
      "automatic_startup": "off",
      "type": "user"
    }
  },
  "display_name": "ADWAPCL",
  "freeform_tags": {},
  "identifier": "ocid1.autonomousdatabase.oc1.eu-frankfurt-1.antheljtnmvrbeaaige7i6wctf7irck4l4zip253afkdeu7l6ydhm34jpmna",
  "identity_context": {},
  "lifecycle_state": "STOPPED",
  "resource_type": "AutonomousDatabase",
  "search_context": null,
  "system_tags": {},
  "time_created": "2021-08-12T08:21:05.473000+00:00"
}, {
  "additional_details": {},
  "availability_domain": null,
  "compartment_id": "ocid1.compartment.oc1..aaaaaaaa5hezxb625e2jesof6g4bt2wuzndxz6bf4pvkjzhecies4wvc44jq",
  "defined_tags": {
    "Oracle-Tags": {
      "CreatedBy": "ocid1.saml2idp.oc1..aaaaaaaa3t6a3psdiskffrvylozoz3mvi7l7tc3idvsqrpes2c7ssghc7kqa/rob.watson@oracle.com"
    },
    "osc": {
      "created-by": "ocid1.saml2idp.oc1..aaaaaaaa3t6a3psdiskffrvylozoz3mvi7l7tc3idvsqrpes2c7ssghc7kqa/rob.watson@oracle.com\t",
      "date": "2020-03-30T15:10:36.393Z",
      "type": "user"
    }
  },
  "display_name": "DBSEC-CLONE-TEST",
  "freeform_tags": {},
  "identifier": "ocid1.image.oc1.eu-frankfurt-1.aaaaaaaair6ynq7wxq43yl7oy52xllixayimmyuci2shzj6a76keiczs4zbq",
  "identity_context": {},
  "lifecycle_state": "Deleted",
  "resource_type": "Image",
  "search_context": null,
  "system_tags": {},
  "time_created": "2020-03-30T15:10:37.018000+00:00"
}, {
  "additional_details": {},
  "availability_domain": null,
  "compartment_id": "ocid1.compartment.oc1..aaaaaaaa5hezxb625e2jesof6g4bt2wuzndxz6bf4pvkjzhecies4wvc44jq",
  "defined_tags": {
    "osc": {
      "automatic_shutdown": "17:00_UTC",
      "automatic_startup": "07:00_UTC",
      "created-by": "oscemea001/rob.watson@oracle.com\t",
      "date": "2020-05-08T21:38:36.300Z",
      "type": "user"
    }
  },
  "display_name": "DBSEC_19C_DB_VER2",
  "freeform_tags": {},
  "identifier": "ocid1.image.oc1.eu-frankfurt-1.aaaaaaaatsmwx4i33evfebcckdir2kh64ijb5nmuutk5r2xcgxzrmj6p5sqa",
  "identity_context": {},
  "lifecycle_state": "Deleted",
  "resource_type": "Image",
  "search_context": null,
  "system_tags": {},
  "time_created": "2020-05-08T21:38:36.437000+00:00"
}, {
  "additional_details": {},
  "availability_domain": "",
  "compartment_id": "ocid1.compartment.oc1..aaaaaaaa5hezxb625e2jesof6g4bt2wuzndxz6bf4pvkjzhecies4wvc44jq",
  "defined_tags": {
    "Oracle-Tags": {
      "CreatedBy": "rob.watson@oracle.com"
    },
    "osc": {
      "created-by": "rob.watson@oracle.com\t",
      "date": "2020-03-19T12:18:12.875Z",
      "type": "user"
    }
  },
  "display_name": "VMs",
  "freeform_tags": {},
  "identifier": "ocid1.bucket.oc1.eu-frankfurt-1.aaaaaaaavoagtamknetmvvgov6ucdlzcdwtnkoamotykemqefxor3c6tiauq",
  "identity_context": {},
  "lifecycle_state": "active",
  "resource_type": "Bucket",
  "search_context": null,
  "system_tags": {},
  "time_created": "2020-03-19T12:18:12.901000+00:00"
}, {
  "additional_details": {},
  "availability_domain": null,
  "compartment_id": "ocid1.compartment.oc1..aaaaaaaa5hezxb625e2jesof6g4bt2wuzndxz6bf4pvkjzhecies4wvc44jq",
  "defined_tags": {},
  "display_name": "VMs",
  "freeform_tags": {},
  "identifier": "ocid1.loganalyticsentity.oc1.eu-frankfurt-1.amaaaaaanmvrbeaacyhexytw7go5qhfu2yghinqtfv3lmkgxenfppenqgfkq",
  "identity_context": {},
  "lifecycle_state": "Active",
  "resource_type": "LogAnalyticsEntity",
  "search_context": null,
  "system_tags": {},
  "time_created": "2021-12-17T09:43:14.810000+00:00"
}, {
  "additional_details": {},
  "availability_domain": null,
  "compartment_id": "ocid1.compartment.oc1..aaaaaaaa5hezxb625e2jesof6g4bt2wuzndxz6bf4pvkjzhecies4wvc44jq",
  "defined_tags": {
    "Oracle-Tags": {
      "CreatedBy": "ocid1.saml2idp.oc1..aaaaaaaa3t6a3psdiskffrvylozoz3mvi7l7tc3idvsqrpes2c7ssghc7kqa/rob.watson@oracle.com"
    },
    "osc": {
      "created-by": "ocid1.saml2idp.oc1..aaaaaaaa3t6a3psdiskffrvylozoz3mvi7l7tc3idvsqrpes2c7ssghc7kqa/rob.watson@oracle.com\t",
      "date": "2020-03-26T12:57:23.275Z",
      "type": "user"
    }
  },
  "display_name": "dbsec19cav",
  "freeform_tags": {},
  "identifier": "ocid1.image.oc1.eu-frankfurt-1.aaaaaaaaic2ogeymb5xgnqxr52d3tg3xvujq42ablzk2ogesfync26fwwbbq",
  "identity_context": {},
  "lifecycle_state": "Deleted",
  "resource_type": "Image",
  "search_context": null,
  "system_tags": {},
  "time_created": "2020-03-26T12:57:23.450000+00:00"
}, {
  "additional_details": {},
  "availability_domain": null,
  "compartment_id": "ocid1.compartment.oc1..aaaaaaaa5hezxb625e2jesof6g4bt2wuzndxz6bf4pvkjzhecies4wvc44jq",
  "defined_tags": {
    "Oracle-Tags": {
      "CreatedBy": "ocid1.saml2idp.oc1..aaaaaaaa3t6a3psdiskffrvylozoz3mvi7l7tc3idvsqrpes2c7ssghc7kqa/rob.watson@oracle.com"
    },
    "osc": {
      "created-by": "ocid1.saml2idp.oc1..aaaaaaaa3t6a3psdiskffrvylozoz3mvi7l7tc3idvsqrpes2c7ssghc7kqa/rob.watson@oracle.com\t",
      "date": "2020-03-26T10:18:42.037Z",
      "type": "user"
    }
  },
  "display_name": "dbsec19cdb",
  "freeform_tags": {},
  "identifier": "ocid1.image.oc1.eu-frankfurt-1.aaaaaaaa6phkd2sgwma6aqudte7vo66eqdzeyfnun7ijtkmcz3723utycjea",
  "identity_context": {},
  "lifecycle_state": "Deleted",
  "resource_type": "Image",
  "search_context": null,
  "system_tags": {},
  "time_created": "2020-03-26T10:18:42.242000+00:00"
}, {
  "additional_details": {},
  "availability_domain": null,
  "compartment_id": "ocid1.compartment.oc1..aaaaaaaa5hezxb625e2jesof6g4bt2wuzndxz6bf4pvkjzhecies4wvc44jq",
  "defined_tags": {
    "Oracle-Tags": {
      "CreatedBy": "ocid1.saml2idp.oc1..aaaaaaaa3t6a3psdiskffrvylozoz3mvi7l7tc3idvsqrpes2c7ssghc7kqa/rob.watson@oracle.com"
    },
    "osc": {
      "created-by": "ocid1.saml2idp.oc1..aaaaaaaa3t6a3psdiskffrvylozoz3mvi7l7tc3idvsqrpes2c7ssghc7kqa/rob.watson@oracle.com\t",
      "date": "2020-03-26T15:51:12.846Z",
      "type": "user"
    }
  },
  "display_name": "dbsec19cfw",
  "freeform_tags": {},
  "identifier": "ocid1.image.oc1.eu-frankfurt-1.aaaaaaaaa7pbwguwaxygcyvkm22jdniri7jcu5fhemitjkyawrfpib7mwhza",
  "identity_context": {},
  "lifecycle_state": "Deleted",
  "resource_type": "Image",
  "search_context": null,
  "system_tags": {},
  "time_created": "2020-03-26T15:51:13.079000+00:00"
}, {
  "additional_details": {},
  "availability_domain": null,
  "compartment_id": "ocid1.compartment.oc1..aaaaaaaa5hezxb625e2jesof6g4bt2wuzndxz6bf4pvkjzhecies4wvc44jq",
  "defined_tags": {
    "Oracle-Tags": {
      "CreatedBy": "ocid1.saml2idp.oc1..aaaaaaaa3t6a3psdiskffrvylozoz3mvi7l7tc3idvsqrpes2c7ssghc7kqa/rob.watson@oracle.com"
    },
    "osc": {
      "created-by": "ocid1.saml2idp.oc1..aaaaaaaa3t6a3psdiskffrvylozoz3mvi7l7tc3idvsqrpes2c7ssghc7kqa/rob.watson@oracle.com\t",
      "date": "2020-03-26T18:31:24.846Z",
      "type": "user"
    }
  },
  "display_name": "dbsec19cfw",
  "freeform_tags": {},
  "identifier": "ocid1.image.oc1.eu-frankfurt-1.aaaaaaaaidouroijzkyjpics26mult2cjdpzyk6ezusmvhs7yvpz7ulmgzeq",
  "identity_context": {},
  "lifecycle_state": "Deleted",
  "resource_type": "Image",
  "search_context": null,
  "system_tags": {},
  "time_created": "2020-03-26T18:31:25.046000+00:00"
}, {
  "additional_details": {},
  "availability_domain": null,
  "compartment_id": "ocid1.compartment.oc1..aaaaaaaa5hezxb625e2jesof6g4bt2wuzndxz6bf4pvkjzhecies4wvc44jq",
  "defined_tags": {
    "Oracle-Tags": {
      "CreatedBy": "ocid1.saml2idp.oc1..aaaaaaaa3t6a3psdiskffrvylozoz3mvi7l7tc3idvsqrpes2c7ssghc7kqa/rob.watson@oracle.com"
    },
    "osc": {
      "created-by": "ocid1.saml2idp.oc1..aaaaaaaa3t6a3psdiskffrvylozoz3mvi7l7tc3idvsqrpes2c7ssghc7kqa/rob.watson@oracle.com\t",
      "date": "2020-03-26T19:01:21.497Z",
      "type": "user"
    }
  },
  "display_name": "dbsec19cfw",
  "freeform_tags": {},
  "identifier": "ocid1.image.oc1.eu-frankfurt-1.aaaaaaaailwb2htqkrt2rkllattysbi2zi43cb6nqriehjbeurikw5gljqfq",
  "identity_context": {},
  "lifecycle_state": "Deleted",
  "resource_type": "Image",
  "search_context": null,
  "system_tags": {},
  "time_created": "2020-03-26T19:01:21.698000+00:00"
}, {
  "additional_details": {},
  "availability_domain": null,
  "compartment_id": "ocid1.compartment.oc1..aaaaaaaa5hezxb625e2jesof6g4bt2wuzndxz6bf4pvkjzhecies4wvc44jq",
  "defined_tags": {
    "Oracle-Tags": {
      "CreatedBy": "ocid1.saml2idp.oc1..aaaaaaaa3t6a3psdiskffrvylozoz3mvi7l7tc3idvsqrpes2c7ssghc7kqa/rob.watson@oracle.com"
    },
    "osc": {
      "created-by": "ocid1.saml2idp.oc1..aaaaaaaa3t6a3psdiskffrvylozoz3mvi7l7tc3idvsqrpes2c7ssghc7kqa/rob.watson@oracle.com\t",
      "date": "2020-03-26T16:54:22.972Z",
      "type": "user"
    }
  },
  "display_name": "dbsec19ckv",
  "freeform_tags": {},
  "identifier": "ocid1.image.oc1.eu-frankfurt-1.aaaaaaaadz6qkvv2cbp52ptwdmw6mmym6yfe36e25hi46uflgg7fcvo6bofq",
  "identity_context": {},
  "lifecycle_state": "Deleted",
  "resource_type": "Image",
  "search_context": null,
  "system_tags": {},
  "time_created": "2020-03-26T16:54:23.248000+00:00"
}, {
  "additional_details": {},
  "availability_domain": "",
  "compartment_id": "ocid1.compartment.oc1..aaaaaaaa5hezxb625e2jesof6g4bt2wuzndxz6bf4pvkjzhecies4wvc44jq",
  "defined_tags": {
    "Oracle-Tags": {
      "CreatedBy": "oscemea001/rob.watson@oracle.com",
      "CreatedOn": "2020-10-27T09:37:35.064Z"
    },
    "osc": {
      "automatic_shutdown": "17:00_UTC",
      "automatic_startup": "07:00_UTC",
      "type": "user"
    }
  },
  "display_name": "Pres",
  "freeform_tags": {},
  "identifier": "ocid1.bucket.oc1.uk-london-1.aaaaaaaakeyevi7lb2snrc5wrhdv7o65lujw2aph3hzrggsxfa3wtafs2oqa",
  "identity_context": {},
  "lifecycle_state": "active",
  "resource_type": "Bucket",
  "search_context": null,
  "system_tags": {},
  "time_created": "2020-10-27T09:37:35.091000+00:00"
}, {
  "additional_details": {},
  "availability_domain": null,
  "compartment_id": "ocid1.compartment.oc1..aaaaaaaa5hezxb625e2jesof6g4bt2wuzndxz6bf4pvkjzhecies4wvc44jq",
  "defined_tags": {},
  "display_name": "Pres",
  "freeform_tags": {},
  "identifier": "ocid1.loganalyticsentity.oc1.uk-london-1.amaaaaaanmvrbeaa2m6l7exud4un5pmr2nu42owukyd6bnc435gipv2irhmq",
  "identity_context": {},
  "lifecycle_state": "Active",
  "resource_type": "LogAnalyticsEntity",
  "search_context": null,
  "system_tags": {},
  "time_created": "2021-12-17T10:37:25.808000+00:00"
}, {
  "additional_details": {},
  "availability_domain": null,
  "compartment_id": "ocid1.compartment.oc1..aaaaaaaa5hezxb625e2jesof6g4bt2wuzndxz6bf4pvkjzhecies4wvc44jq",
  "defined_tags": {},
  "display_name": "UA_1658563318115",
  "freeform_tags": {},
  "identifier": "ocid1.datasafeuserassessment.oc1.uk-london-1.abwgiljsgqozgu6pseh6tw6cycusk64444iebsyqi4bid6swcdpl36xfe7tq",
  "identity_context": {},
  "lifecycle_state": "SUCCEEDED",
  "resource_type": "DataSafeUserAssessment",
  "search_context": null,
  "system_tags": {},
  "time_created": "2022-07-23T08:01:58.122000+00:00"
}]