[{
  "additional_details": {},
  "availability_domain": null,
  "compartment_id": "ocid1.compartment.oc1..aaaaaaaapx5ehkw7y2l26nu5s4ybs3a4tfh6paeex3o4psmw6sed4hckzona",
  "defined_tags": {
    "Oracle-Tags": {
      "CreatedBy": "oscemea001/eric.vinck@oracle.com",
      "CreatedOn": "2023-02-22T14:54:13.899Z"
    },
    "osc": {
      "automatic_shutdown": "17:00_UTC",
      "automatic_startup": "07:00_UTC",
      "type": "user"
    }
  },
  "display_name": "0.10.in-addr.arpa",
  "freeform_tags": {
    "VCN": "VCN-2023-02-22T14:52:43"
  },
  "identifier": "ocid1.dns-zone.oc1.eu-frankfurt-1.aaaaaaaaksikhhlayossx3avnlwxivogrtp6rkxghf73zalksx3c67gtwjba",
  "identity_context": {},
  "lifecycle_state": "ACTIVE",
  "resource_type": "CustomerDnsZone",
  "search_context": null,
  "system_tags": {},
  "time_created": "2023-02-22T14:54:16.333000+00:00"
}, {
  "additional_details": {},
  "availability_domain": null,
  "compartment_id": "ocid1.compartment.oc1..aaaaaaaapx5ehkw7y2l26nu5s4ybs3a4tfh6paeex3o4psmw6sed4hckzona",
  "defined_tags": {
    "Oracle-Tags": {
      "CreatedBy": "oscemea001/eric.vinck@oracle.com",
      "CreatedOn": "2023-02-22T14:54:15.012Z"
    },
    "osc": {
      "automatic_shutdown": "17:00_UTC",
      "automatic_startup": "07:00_UTC",
      "type": "user"
    }
  },
  "display_name": "sub02221454100.mdsvcn.oraclevcn.com",
  "freeform_tags": {
    "VCN": "VCN-2023-02-22T14:52:43"
  },
  "identifier": "ocid1.dns-zone.oc1.eu-frankfurt-1.aaaaaaaak5dodpvnci54hxlas6sixhx74jyifgtvbnm676arcmqllc4jtjwa",
  "identity_context": {},
  "lifecycle_state": "ACTIVE",
  "resource_type": "CustomerDnsZone",
  "search_context": null,
  "system_tags": {},
  "time_created": "2023-02-22T14:54:17.259000+00:00"
}, {
  "additional_details": {},
  "availability_domain": null,
  "compartment_id": "ocid1.compartment.oc1..aaaaaaaapx5ehkw7y2l26nu5s4ybs3a4tfh6paeex3o4psmw6sed4hckzona",
  "defined_tags": {
    "Oracle-Tags": {
      "CreatedBy": "oscemea001/eric.vinck@oracle.com",
      "CreatedOn": "2023-02-22T14:54:14.947Z"
    },
    "osc": {
      "automatic_shutdown": "17:00_UTC",
      "automatic_startup": "07:00_UTC",
      "type": "user"
    }
  },
  "display_name": "sub02221454101.mdsvcn.oraclevcn.com",
  "freeform_tags": {
    "VCN": "VCN-2023-02-22T14:52:43"
  },
  "identifier": "ocid1.dns-zone.oc1.eu-frankfurt-1.aaaaaaaahxdagocepw7jie3e4kpfnb6y27irkmspnrxirlccoqazforlpzjq",
  "identity_context": {},
  "lifecycle_state": "ACTIVE",
  "resource_type": "CustomerDnsZone",
  "search_context": null,
  "system_tags": {},
  "time_created": "2023-02-22T14:54:18.193000+00:00"
}]